{
  "currentSyncroStatus": 0,
  "assignedApplications": [
    1,
    234,
    293,
    2,
    173,
    133,
    213,
    -1
  ],
  "assignedTestSuiteIDs": [
    1664
  ],
  "version": null,
  "assignedDataSets": [
    {
      "recordStatus": 0,
      "DATA_SUMMARY_ID": 288014,
      "ALIAS_NAME": "Auto Rate Reset tc",
      "DESCRIPTION_INFO": null
    }
  ],
  "allSteps": [
    {
      "dataForDataSets": [
        {
          "Data_Setting_Id": 280694,
          "DATASETVALUE": null,
          "DATA_SUMMARY_ID": 288014,
          "SKIP": 0,
          "STEPS_ID": 288016
        }
      ],
      "recordStatus": 0,
      "TEST_CASE_ID": 3245,
      "TEST_CASE_NAME": "Auto Rate Reset tc",
      "KEY_WORD_ID": 15,
      "KEY_WORD_NAME": "PegWindow",
      "OBJECT_HAPPY_NAME": "Summit Start",
      "OBJECT_ID": 38857,
      "OBJECT_TYPE": "Summit Start",
      "QUICK_ACCESS": "is owned window:=False\r\nis child window:=False\r\ntext:=((Misys|Finastra ){0,1}(FusionCapital|Fusion ){0,1}(Markets ){0,1}Summit( FT){0,1})(?!(.*Login)).*\r\nindex:=0",
      "ENUM_TYPE": null,
      "APPLICATION_ID": 234,
      "OBJECT_NAME_ID": 11892,
      "TYPE_NAME": "Pegwindow",
      "STEPS_ID": 288016,
      "COLUMN_ROW_SETTING": null,
      "COMMENTINFO": null,
      "IS_RUNNABLE": 0,
      "RUN_ORDER": 1,
      "VALUE_SETTING": null
    },
    {
      "dataForDataSets": [
        {
          "Data_Setting_Id": 280694,
          "DATASETVALUE": null,
          "DATA_SUMMARY_ID": 288014,
          "SKIP": 0,
          "STEPS_ID": 288016
        }
      ],
      "recordStatus": 0,
      "TEST_CASE_ID": 3245,
      "TEST_CASE_NAME": "Auto Rate Reset tc",
      "KEY_WORD_ID": 15,
      "KEY_WORD_NAME": "PegWindow",
      "OBJECT_HAPPY_NAME": "Summit Start",
      "OBJECT_ID": 46255,
      "OBJECT_TYPE": "Summit Start",
      "QUICK_ACCESS": "is owned window:=False\r\nis child window:=False\r\ntext:=((Misys|Finastra ){0,1}(FusionCapital|Fusion ){0,1}(Markets ){0,1}Summit( FT){0,1})(?!(.*Login)).*\r\nindex:=0",
      "ENUM_TYPE": null,
      "APPLICATION_ID": 293,
      "OBJECT_NAME_ID": 11892,
      "TYPE_NAME": "Pegwindow",
      "STEPS_ID": 288016,
      "COLUMN_ROW_SETTING": null,
      "COMMENTINFO": null,
      "IS_RUNNABLE": 0,
      "RUN_ORDER": 1,
      "VALUE_SETTING": null
    },
    {
      "dataForDataSets": [
        {
          "Data_Setting_Id": 280694,
          "DATASETVALUE": null,
          "DATA_SUMMARY_ID": 288014,
          "SKIP": 0,
          "STEPS_ID": 288016
        }
      ],
      "recordStatus": 0,
      "TEST_CASE_ID": 3245,
      "TEST_CASE_NAME": "Auto Rate Reset tc",
      "KEY_WORD_ID": 15,
      "KEY_WORD_NAME": "PegWindow",
      "OBJECT_HAPPY_NAME": "Summit Start",
      "OBJECT_ID": 3893,
      "OBJECT_TYPE": "Summit Start",
      "QUICK_ACCESS": "is owned window:=False\nis child window:=False\ntext:=((Misys ){0,1}(FusionCapital ){0,1}Summit( FT){0,1})(?!(.*Login)).*\r\nindex:=0",
      "ENUM_TYPE": null,
      "APPLICATION_ID": 2,
      "OBJECT_NAME_ID": 11892,
      "TYPE_NAME": "Pegwindow",
      "STEPS_ID": 288016,
      "COLUMN_ROW_SETTING": null,
      "COMMENTINFO": null,
      "IS_RUNNABLE": 0,
      "RUN_ORDER": 1,
      "VALUE_SETTING": null
    },
    {
      "dataForDataSets": [
        {
          "Data_Setting_Id": 280694,
          "DATASETVALUE": null,
          "DATA_SUMMARY_ID": 288014,
          "SKIP": 0,
          "STEPS_ID": 288016
        }
      ],
      "recordStatus": 0,
      "TEST_CASE_ID": 3245,
      "TEST_CASE_NAME": "Auto Rate Reset tc",
      "KEY_WORD_ID": 15,
      "KEY_WORD_NAME": "PegWindow",
      "OBJECT_HAPPY_NAME": "Summit Start",
      "OBJECT_ID": 61,
      "OBJECT_TYPE": "Summit Start",
      "QUICK_ACCESS": "is owned window:=False\r\nis child window:=False\r\ntext:=((Misys|Finastra ){0,1}(FusionCapital|Fusion ){0,1}(Markets ){0,1}Summit( FT){0,1})(?!(.*Login)).*\r\nindex:=0",
      "ENUM_TYPE": null,
      "APPLICATION_ID": 1,
      "OBJECT_NAME_ID": 11892,
      "TYPE_NAME": "Pegwindow",
      "STEPS_ID": 288016,
      "COLUMN_ROW_SETTING": null,
      "COMMENTINFO": null,
      "IS_RUNNABLE": 0,
      "RUN_ORDER": 1,
      "VALUE_SETTING": null
    },
    {
      "dataForDataSets": [
        {
          "Data_Setting_Id": 280694,
          "DATASETVALUE": null,
          "DATA_SUMMARY_ID": 288014,
          "SKIP": 0,
          "STEPS_ID": 288016
        }
      ],
      "recordStatus": 0,
      "TEST_CASE_ID": 3245,
      "TEST_CASE_NAME": "Auto Rate Reset tc",
      "KEY_WORD_ID": 15,
      "KEY_WORD_NAME": "PegWindow",
      "OBJECT_HAPPY_NAME": "Summit Start",
      "OBJECT_ID": 16827,
      "OBJECT_TYPE": "Summit Start",
      "QUICK_ACCESS": "is owned window:=False\nis child window:=False\ntext:=((Misys ){0,1}(FusionCapital ){0,1}Summit( FT){0,1})(?!(.*Login)).*\r\nindex:=0",
      "ENUM_TYPE": null,
      "APPLICATION_ID": 173,
      "OBJECT_NAME_ID": 11892,
      "TYPE_NAME": "Pegwindow",
      "STEPS_ID": 288016,
      "COLUMN_ROW_SETTING": null,
      "COMMENTINFO": null,
      "IS_RUNNABLE": 0,
      "RUN_ORDER": 1,
      "VALUE_SETTING": null
    },
    {
      "dataForDataSets": [
        {
          "Data_Setting_Id": 280694,
          "DATASETVALUE": null,
          "DATA_SUMMARY_ID": 288014,
          "SKIP": 0,
          "STEPS_ID": 288016
        }
      ],
      "recordStatus": 0,
      "TEST_CASE_ID": 3245,
      "TEST_CASE_NAME": "Auto Rate Reset tc",
      "KEY_WORD_ID": 15,
      "KEY_WORD_NAME": "PegWindow",
      "OBJECT_HAPPY_NAME": "Summit Start",
      "OBJECT_ID": 20724,
      "OBJECT_TYPE": "Summit Start",
      "QUICK_ACCESS": "is owned window:=False\nis child window:=False\ntext:=(Misys ){0,1}Summit FT.*",
      "ENUM_TYPE": null,
      "APPLICATION_ID": 133,
      "OBJECT_NAME_ID": 11892,
      "TYPE_NAME": "Pegwindow",
      "STEPS_ID": 288016,
      "COLUMN_ROW_SETTING": null,
      "COMMENTINFO": null,
      "IS_RUNNABLE": 0,
      "RUN_ORDER": 1,
      "VALUE_SETTING": null
    },
    {
      "dataForDataSets": [
        {
          "Data_Setting_Id": 280694,
          "DATASETVALUE": null,
          "DATA_SUMMARY_ID": 288014,
          "SKIP": 0,
          "STEPS_ID": 288016
        }
      ],
      "recordStatus": 0,
      "TEST_CASE_ID": 3245,
      "TEST_CASE_NAME": "Auto Rate Reset tc",
      "KEY_WORD_ID": 15,
      "KEY_WORD_NAME": "PegWindow",
      "OBJECT_HAPPY_NAME": "Summit Start",
      "OBJECT_ID": 32573,
      "OBJECT_TYPE": "Summit Start",
      "QUICK_ACCESS": "is owned window:=False\nis child window:=False\ntext:=((Misys ){0,1}(FusionCapital ){0,1}Summit( FT){0,1})(?!(.*Login)).*\r\nindex:=0",
      "ENUM_TYPE": null,
      "APPLICATION_ID": 213,
      "OBJECT_NAME_ID": 11892,
      "TYPE_NAME": "Pegwindow",
      "STEPS_ID": 288016,
      "COLUMN_ROW_SETTING": null,
      "COMMENTINFO": null,
      "IS_RUNNABLE": 0,
      "RUN_ORDER": 1,
      "VALUE_SETTING": null
    },
    {
      "dataForDataSets": [
        {
          "Data_Setting_Id": 280686,
          "DATASETVALUE": null,
          "DATA_SUMMARY_ID": 288014,
          "SKIP": 0,
          "STEPS_ID": 288169
        }
      ],
      "recordStatus": 0,
      "TEST_CASE_ID": 3245,
      "TEST_CASE_NAME": "Auto Rate Reset tc",
      "KEY_WORD_ID": 14,
      "KEY_WORD_NAME": "MaximizeWindow",
      "OBJECT_HAPPY_NAME": "Summit Start",
      "OBJECT_ID": 38857,
      "OBJECT_TYPE": "Summit Start",
      "QUICK_ACCESS": "is owned window:=False\r\nis child window:=False\r\ntext:=((Misys|Finastra ){0,1}(FusionCapital|Fusion ){0,1}(Markets ){0,1}Summit( FT){0,1})(?!(.*Login)).*\r\nindex:=0",
      "ENUM_TYPE": null,
      "APPLICATION_ID": 234,
      "OBJECT_NAME_ID": 11892,
      "TYPE_NAME": "Pegwindow",
      "STEPS_ID": 288169,
      "COLUMN_ROW_SETTING": null,
      "COMMENTINFO": null,
      "IS_RUNNABLE": 0,
      "RUN_ORDER": 2,
      "VALUE_SETTING": null
    },
    {
      "dataForDataSets": [
        {
          "Data_Setting_Id": 280686,
          "DATASETVALUE": null,
          "DATA_SUMMARY_ID": 288014,
          "SKIP": 0,
          "STEPS_ID": 288169
        }
      ],
      "recordStatus": 0,
      "TEST_CASE_ID": 3245,
      "TEST_CASE_NAME": "Auto Rate Reset tc",
      "KEY_WORD_ID": 14,
      "KEY_WORD_NAME": "MaximizeWindow",
      "OBJECT_HAPPY_NAME": "Summit Start",
      "OBJECT_ID": 46255,
      "OBJECT_TYPE": "Summit Start",
      "QUICK_ACCESS": "is owned window:=False\r\nis child window:=False\r\ntext:=((Misys|Finastra ){0,1}(FusionCapital|Fusion ){0,1}(Markets ){0,1}Summit( FT){0,1})(?!(.*Login)).*\r\nindex:=0",
      "ENUM_TYPE": null,
      "APPLICATION_ID": 293,
      "OBJECT_NAME_ID": 11892,
      "TYPE_NAME": "Pegwindow",
      "STEPS_ID": 288169,
      "COLUMN_ROW_SETTING": null,
      "COMMENTINFO": null,
      "IS_RUNNABLE": 0,
      "RUN_ORDER": 2,
      "VALUE_SETTING": null
    },
    {
      "dataForDataSets": [
        {
          "Data_Setting_Id": 280686,
          "DATASETVALUE": null,
          "DATA_SUMMARY_ID": 288014,
          "SKIP": 0,
          "STEPS_ID": 288169
        }
      ],
      "recordStatus": 0,
      "TEST_CASE_ID": 3245,
      "TEST_CASE_NAME": "Auto Rate Reset tc",
      "KEY_WORD_ID": 14,
      "KEY_WORD_NAME": "MaximizeWindow",
      "OBJECT_HAPPY_NAME": "Summit Start",
      "OBJECT_ID": 3893,
      "OBJECT_TYPE": "Summit Start",
      "QUICK_ACCESS": "is owned window:=False\nis child window:=False\ntext:=((Misys ){0,1}(FusionCapital ){0,1}Summit( FT){0,1})(?!(.*Login)).*\r\nindex:=0",
      "ENUM_TYPE": null,
      "APPLICATION_ID": 2,
      "OBJECT_NAME_ID": 11892,
      "TYPE_NAME": "Pegwindow",
      "STEPS_ID": 288169,
      "COLUMN_ROW_SETTING": null,
      "COMMENTINFO": null,
      "IS_RUNNABLE": 0,
      "RUN_ORDER": 2,
      "VALUE_SETTING": null
    },
    {
      "dataForDataSets": [
        {
          "Data_Setting_Id": 280686,
          "DATASETVALUE": null,
          "DATA_SUMMARY_ID": 288014,
          "SKIP": 0,
          "STEPS_ID": 288169
        }
      ],
      "recordStatus": 0,
      "TEST_CASE_ID": 3245,
      "TEST_CASE_NAME": "Auto Rate Reset tc",
      "KEY_WORD_ID": 14,
      "KEY_WORD_NAME": "MaximizeWindow",
      "OBJECT_HAPPY_NAME": "Summit Start",
      "OBJECT_ID": 61,
      "OBJECT_TYPE": "Summit Start",
      "QUICK_ACCESS": "is owned window:=False\r\nis child window:=False\r\ntext:=((Misys|Finastra ){0,1}(FusionCapital|Fusion ){0,1}(Markets ){0,1}Summit( FT){0,1})(?!(.*Login)).*\r\nindex:=0",
      "ENUM_TYPE": null,
      "APPLICATION_ID": 1,
      "OBJECT_NAME_ID": 11892,
      "TYPE_NAME": "Pegwindow",
      "STEPS_ID": 288169,
      "COLUMN_ROW_SETTING": null,
      "COMMENTINFO": null,
      "IS_RUNNABLE": 0,
      "RUN_ORDER": 2,
      "VALUE_SETTING": null
    },
    {
      "dataForDataSets": [
        {
          "Data_Setting_Id": 280686,
          "DATASETVALUE": null,
          "DATA_SUMMARY_ID": 288014,
          "SKIP": 0,
          "STEPS_ID": 288169
        }
      ],
      "recordStatus": 0,
      "TEST_CASE_ID": 3245,
      "TEST_CASE_NAME": "Auto Rate Reset tc",
      "KEY_WORD_ID": 14,
      "KEY_WORD_NAME": "MaximizeWindow",
      "OBJECT_HAPPY_NAME": "Summit Start",
      "OBJECT_ID": 16827,
      "OBJECT_TYPE": "Summit Start",
      "QUICK_ACCESS": "is owned window:=False\nis child window:=False\ntext:=((Misys ){0,1}(FusionCapital ){0,1}Summit( FT){0,1})(?!(.*Login)).*\r\nindex:=0",
      "ENUM_TYPE": null,
      "APPLICATION_ID": 173,
      "OBJECT_NAME_ID": 11892,
      "TYPE_NAME": "Pegwindow",
      "STEPS_ID": 288169,
      "COLUMN_ROW_SETTING": null,
      "COMMENTINFO": null,
      "IS_RUNNABLE": 0,
      "RUN_ORDER": 2,
      "VALUE_SETTING": null
    },
    {
      "dataForDataSets": [
        {
          "Data_Setting_Id": 280686,
          "DATASETVALUE": null,
          "DATA_SUMMARY_ID": 288014,
          "SKIP": 0,
          "STEPS_ID": 288169
        }
      ],
      "recordStatus": 0,
      "TEST_CASE_ID": 3245,
      "TEST_CASE_NAME": "Auto Rate Reset tc",
      "KEY_WORD_ID": 14,
      "KEY_WORD_NAME": "MaximizeWindow",
      "OBJECT_HAPPY_NAME": "Summit Start",
      "OBJECT_ID": 20724,
      "OBJECT_TYPE": "Summit Start",
      "QUICK_ACCESS": "is owned window:=False\nis child window:=False\ntext:=(Misys ){0,1}Summit FT.*",
      "ENUM_TYPE": null,
      "APPLICATION_ID": 133,
      "OBJECT_NAME_ID": 11892,
      "TYPE_NAME": "Pegwindow",
      "STEPS_ID": 288169,
      "COLUMN_ROW_SETTING": null,
      "COMMENTINFO": null,
      "IS_RUNNABLE": 0,
      "RUN_ORDER": 2,
      "VALUE_SETTING": null
    },
    {
      "dataForDataSets": [
        {
          "Data_Setting_Id": 280686,
          "DATASETVALUE": null,
          "DATA_SUMMARY_ID": 288014,
          "SKIP": 0,
          "STEPS_ID": 288169
        }
      ],
      "recordStatus": 0,
      "TEST_CASE_ID": 3245,
      "TEST_CASE_NAME": "Auto Rate Reset tc",
      "KEY_WORD_ID": 14,
      "KEY_WORD_NAME": "MaximizeWindow",
      "OBJECT_HAPPY_NAME": "Summit Start",
      "OBJECT_ID": 32573,
      "OBJECT_TYPE": "Summit Start",
      "QUICK_ACCESS": "is owned window:=False\nis child window:=False\ntext:=((Misys ){0,1}(FusionCapital ){0,1}Summit( FT){0,1})(?!(.*Login)).*\r\nindex:=0",
      "ENUM_TYPE": null,
      "APPLICATION_ID": 213,
      "OBJECT_NAME_ID": 11892,
      "TYPE_NAME": "Pegwindow",
      "STEPS_ID": 288169,
      "COLUMN_ROW_SETTING": null,
      "COMMENTINFO": null,
      "IS_RUNNABLE": 0,
      "RUN_ORDER": 2,
      "VALUE_SETTING": null
    },
    {
      "dataForDataSets": [
        {
          "Data_Setting_Id": 280690,
          "DATASETVALUE": "Auto Rate Reset",
          "DATA_SUMMARY_ID": 288014,
          "SKIP": 0,
          "STEPS_ID": 288173
        }
      ],
      "recordStatus": 0,
      "TEST_CASE_ID": 3245,
      "TEST_CASE_NAME": "Auto Rate Reset tc",
      "KEY_WORD_ID": 12,
      "KEY_WORD_NAME": "LaunchApplication",
      "OBJECT_HAPPY_NAME": "ApplicationName",
      "OBJECT_ID": 43872,
      "OBJECT_TYPE": "Summit Start",
      "QUICK_ACCESS": "swfname:=_toolbarsDockAreaTop",
      "ENUM_TYPE": null,
      "APPLICATION_ID": 293,
      "OBJECT_NAME_ID": 14837,
      "TYPE_NAME": "SwfToolBar",
      "STEPS_ID": 288173,
      "COLUMN_ROW_SETTING": null,
      "COMMENTINFO": null,
      "IS_RUNNABLE": 0,
      "RUN_ORDER": 3,
      "VALUE_SETTING": null
    },
    {
      "dataForDataSets": [
        {
          "Data_Setting_Id": 280690,
          "DATASETVALUE": "Auto Rate Reset",
          "DATA_SUMMARY_ID": 288014,
          "SKIP": 0,
          "STEPS_ID": 288173
        }
      ],
      "recordStatus": 0,
      "TEST_CASE_ID": 3245,
      "TEST_CASE_NAME": "Auto Rate Reset tc",
      "KEY_WORD_ID": 12,
      "KEY_WORD_NAME": "LaunchApplication",
      "OBJECT_HAPPY_NAME": "ApplicationName",
      "OBJECT_ID": 36474,
      "OBJECT_TYPE": "Summit Start",
      "QUICK_ACCESS": "swfname:=_toolbarsDockAreaTop",
      "ENUM_TYPE": null,
      "APPLICATION_ID": 234,
      "OBJECT_NAME_ID": 14837,
      "TYPE_NAME": "SwfToolBar",
      "STEPS_ID": 288173,
      "COLUMN_ROW_SETTING": null,
      "COMMENTINFO": null,
      "IS_RUNNABLE": 0,
      "RUN_ORDER": 3,
      "VALUE_SETTING": null
    },
    {
      "dataForDataSets": [
        {
          "Data_Setting_Id": 280690,
          "DATASETVALUE": "Auto Rate Reset",
          "DATA_SUMMARY_ID": 288014,
          "SKIP": 0,
          "STEPS_ID": 288173
        }
      ],
      "recordStatus": 0,
      "TEST_CASE_ID": 3245,
      "TEST_CASE_NAME": "Auto Rate Reset tc",
      "KEY_WORD_ID": 12,
      "KEY_WORD_NAME": "LaunchApplication",
      "OBJECT_HAPPY_NAME": "ApplicationName",
      "OBJECT_ID": 3897,
      "OBJECT_TYPE": "Summit Start",
      "QUICK_ACCESS": "swfname:=_toolbarsDockAreaTop",
      "ENUM_TYPE": null,
      "APPLICATION_ID": 2,
      "OBJECT_NAME_ID": 14837,
      "TYPE_NAME": "SwfToolBar",
      "STEPS_ID": 288173,
      "COLUMN_ROW_SETTING": null,
      "COMMENTINFO": null,
      "IS_RUNNABLE": 0,
      "RUN_ORDER": 3,
      "VALUE_SETTING": null
    },
    {
      "dataForDataSets": [
        {
          "Data_Setting_Id": 280690,
          "DATASETVALUE": "Auto Rate Reset",
          "DATA_SUMMARY_ID": 288014,
          "SKIP": 0,
          "STEPS_ID": 288173
        }
      ],
      "recordStatus": 0,
      "TEST_CASE_ID": 3245,
      "TEST_CASE_NAME": "Auto Rate Reset tc",
      "KEY_WORD_ID": 12,
      "KEY_WORD_NAME": "LaunchApplication",
      "OBJECT_HAPPY_NAME": "ApplicationName",
      "OBJECT_ID": 65,
      "OBJECT_TYPE": "Summit Start",
      "QUICK_ACCESS": "swfname:=_toolbarsDockAreaTop",
      "ENUM_TYPE": null,
      "APPLICATION_ID": 1,
      "OBJECT_NAME_ID": 14837,
      "TYPE_NAME": "SwfToolBar",
      "STEPS_ID": 288173,
      "COLUMN_ROW_SETTING": null,
      "COMMENTINFO": null,
      "IS_RUNNABLE": 0,
      "RUN_ORDER": 3,
      "VALUE_SETTING": null
    },
    {
      "dataForDataSets": [
        {
          "Data_Setting_Id": 280690,
          "DATASETVALUE": "Auto Rate Reset",
          "DATA_SUMMARY_ID": 288014,
          "SKIP": 0,
          "STEPS_ID": 288173
        }
      ],
      "recordStatus": 0,
      "TEST_CASE_ID": 3245,
      "TEST_CASE_NAME": "Auto Rate Reset tc",
      "KEY_WORD_ID": 12,
      "KEY_WORD_NAME": "LaunchApplication",
      "OBJECT_HAPPY_NAME": "ApplicationName",
      "OBJECT_ID": 14444,
      "OBJECT_TYPE": "Summit Start",
      "QUICK_ACCESS": "swfname:=_toolbarsDockAreaTop",
      "ENUM_TYPE": null,
      "APPLICATION_ID": 173,
      "OBJECT_NAME_ID": 14837,
      "TYPE_NAME": "SwfToolBar",
      "STEPS_ID": 288173,
      "COLUMN_ROW_SETTING": null,
      "COMMENTINFO": null,
      "IS_RUNNABLE": 0,
      "RUN_ORDER": 3,
      "VALUE_SETTING": null
    },
    {
      "dataForDataSets": [
        {
          "Data_Setting_Id": 280690,
          "DATASETVALUE": "Auto Rate Reset",
          "DATA_SUMMARY_ID": 288014,
          "SKIP": 0,
          "STEPS_ID": 288173
        }
      ],
      "recordStatus": 0,
      "TEST_CASE_ID": 3245,
      "TEST_CASE_NAME": "Auto Rate Reset tc",
      "KEY_WORD_ID": 12,
      "KEY_WORD_NAME": "LaunchApplication",
      "OBJECT_HAPPY_NAME": "ApplicationName",
      "OBJECT_ID": 30667,
      "OBJECT_TYPE": "Summit Start",
      "QUICK_ACCESS": "swfname:=_toolbarsDockAreaTop",
      "ENUM_TYPE": null,
      "APPLICATION_ID": 213,
      "OBJECT_NAME_ID": 14837,
      "TYPE_NAME": "SwfToolBar",
      "STEPS_ID": 288173,
      "COLUMN_ROW_SETTING": null,
      "COMMENTINFO": null,
      "IS_RUNNABLE": 0,
      "RUN_ORDER": 3,
      "VALUE_SETTING": null
    },
    {
      "dataForDataSets": [
        {
          "Data_Setting_Id": 280687,
          "DATASETVALUE": null,
          "DATA_SUMMARY_ID": 288014,
          "SKIP": 0,
          "STEPS_ID": 288170
        }
      ],
      "recordStatus": 0,
      "TEST_CASE_ID": 3245,
      "TEST_CASE_NAME": "Auto Rate Reset tc",
      "KEY_WORD_ID": 15,
      "KEY_WORD_NAME": "PegWindow",
      "OBJECT_HAPPY_NAME": "AUTO_ RATE_RESET",
      "OBJECT_ID": 27513,
      "OBJECT_TYPE": "AUTO_ RATE_RESET",
      "QUICK_ACCESS": "is owned window:=False\nis child window:=False\nText:=^((Misys|Finastra ){0,1}(FusionCapital|Fusion ){0,1}(Markets ){0,1}Summit( FT){0,1})(?!(.*Login)).*",
      "ENUM_TYPE": null,
      "APPLICATION_ID": 1,
      "OBJECT_NAME_ID": 27420,
      "TYPE_NAME": "Pegwindow",
      "STEPS_ID": 288170,
      "COLUMN_ROW_SETTING": null,
      "COMMENTINFO": null,
      "IS_RUNNABLE": 0,
      "RUN_ORDER": 4,
      "VALUE_SETTING": null
    },
    {
      "dataForDataSets": [
        {
          "Data_Setting_Id": 280687,
          "DATASETVALUE": null,
          "DATA_SUMMARY_ID": 288014,
          "SKIP": 0,
          "STEPS_ID": 288170
        }
      ],
      "recordStatus": 0,
      "TEST_CASE_ID": 3245,
      "TEST_CASE_NAME": "Auto Rate Reset tc",
      "KEY_WORD_ID": 15,
      "KEY_WORD_NAME": "PegWindow",
      "OBJECT_HAPPY_NAME": "AUTO_ RATE_RESET",
      "OBJECT_ID": 41245,
      "OBJECT_TYPE": "AUTO_ RATE_RESET",
      "QUICK_ACCESS": "is owned window:=False\nis child window:=False\nText:=^((Misys|Finastra ){0,1}(FusionCapital|Fusion ){0,1}(Markets ){0,1}Summit( FT){0,1})(?!(.*Login)).*",
      "ENUM_TYPE": null,
      "APPLICATION_ID": 234,
      "OBJECT_NAME_ID": 27420,
      "TYPE_NAME": "Pegwindow",
      "STEPS_ID": 288170,
      "COLUMN_ROW_SETTING": null,
      "COMMENTINFO": null,
      "IS_RUNNABLE": 0,
      "RUN_ORDER": 4,
      "VALUE_SETTING": null
    },
    {
      "dataForDataSets": [
        {
          "Data_Setting_Id": 280687,
          "DATASETVALUE": null,
          "DATA_SUMMARY_ID": 288014,
          "SKIP": 0,
          "STEPS_ID": 288170
        }
      ],
      "recordStatus": 0,
      "TEST_CASE_ID": 3245,
      "TEST_CASE_NAME": "Auto Rate Reset tc",
      "KEY_WORD_ID": 15,
      "KEY_WORD_NAME": "PegWindow",
      "OBJECT_HAPPY_NAME": "AUTO_ RATE_RESET",
      "OBJECT_ID": 48643,
      "OBJECT_TYPE": "AUTO_ RATE_RESET",
      "QUICK_ACCESS": "is owned window:=False\nis child window:=False\nText:=^((Misys|Finastra ){0,1}(FusionCapital|Fusion ){0,1}(Markets ){0,1}Summit( FT){0,1})(?!(.*Login)).*",
      "ENUM_TYPE": null,
      "APPLICATION_ID": 293,
      "OBJECT_NAME_ID": 27420,
      "TYPE_NAME": "Pegwindow",
      "STEPS_ID": 288170,
      "COLUMN_ROW_SETTING": null,
      "COMMENTINFO": null,
      "IS_RUNNABLE": 0,
      "RUN_ORDER": 4,
      "VALUE_SETTING": null
    },
    {
      "dataForDataSets": [
        {
          "Data_Setting_Id": 280676,
          "DATASETVALUE": "ACCT_SWAP",
          "DATA_SUMMARY_ID": 288014,
          "SKIP": 0,
          "STEPS_ID": 288157
        }
      ],
      "recordStatus": 0,
      "TEST_CASE_ID": 3245,
      "TEST_CASE_NAME": "Auto Rate Reset tc",
      "KEY_WORD_ID": 10,
      "KEY_WORD_NAME": "FillEdit",
      "OBJECT_HAPPY_NAME": "AUTO_ RATE_RESET_FILTER",
      "OBJECT_ID": 27491,
      "OBJECT_TYPE": "AUTO_ RATE_RESET",
      "QUICK_ACCESS": "swfname:=_filterEntry",
      "ENUM_TYPE": null,
      "APPLICATION_ID": 1,
      "OBJECT_NAME_ID": 27445,
      "TYPE_NAME": "SwfEdit",
      "STEPS_ID": 288157,
      "COLUMN_ROW_SETTING": null,
      "COMMENTINFO": null,
      "IS_RUNNABLE": 0,
      "RUN_ORDER": 5,
      "VALUE_SETTING": null
    },
    {
      "dataForDataSets": [
        {
          "Data_Setting_Id": 280676,
          "DATASETVALUE": "ACCT_SWAP",
          "DATA_SUMMARY_ID": 288014,
          "SKIP": 0,
          "STEPS_ID": 288157
        }
      ],
      "recordStatus": 0,
      "TEST_CASE_ID": 3245,
      "TEST_CASE_NAME": "Auto Rate Reset tc",
      "KEY_WORD_ID": 10,
      "KEY_WORD_NAME": "FillEdit",
      "OBJECT_HAPPY_NAME": "AUTO_ RATE_RESET_FILTER",
      "OBJECT_ID": 41223,
      "OBJECT_TYPE": "AUTO_ RATE_RESET",
      "QUICK_ACCESS": "swfname:=_filterEntry",
      "ENUM_TYPE": null,
      "APPLICATION_ID": 234,
      "OBJECT_NAME_ID": 27445,
      "TYPE_NAME": "SwfEdit",
      "STEPS_ID": 288157,
      "COLUMN_ROW_SETTING": null,
      "COMMENTINFO": null,
      "IS_RUNNABLE": 0,
      "RUN_ORDER": 5,
      "VALUE_SETTING": null
    },
    {
      "dataForDataSets": [
        {
          "Data_Setting_Id": 280676,
          "DATASETVALUE": "ACCT_SWAP",
          "DATA_SUMMARY_ID": 288014,
          "SKIP": 0,
          "STEPS_ID": 288157
        }
      ],
      "recordStatus": 0,
      "TEST_CASE_ID": 3245,
      "TEST_CASE_NAME": "Auto Rate Reset tc",
      "KEY_WORD_ID": 10,
      "KEY_WORD_NAME": "FillEdit",
      "OBJECT_HAPPY_NAME": "AUTO_ RATE_RESET_FILTER",
      "OBJECT_ID": 48621,
      "OBJECT_TYPE": "AUTO_ RATE_RESET",
      "QUICK_ACCESS": "swfname:=_filterEntry",
      "ENUM_TYPE": null,
      "APPLICATION_ID": 293,
      "OBJECT_NAME_ID": 27445,
      "TYPE_NAME": "SwfEdit",
      "STEPS_ID": 288157,
      "COLUMN_ROW_SETTING": null,
      "COMMENTINFO": null,
      "IS_RUNNABLE": 0,
      "RUN_ORDER": 5,
      "VALUE_SETTING": null
    },
    {
      "dataForDataSets": [
        {
          "Data_Setting_Id": 280698,
          "DATASETVALUE": null,
          "DATA_SUMMARY_ID": 288014,
          "SKIP": 0,
          "STEPS_ID": 288161
        }
      ],
      "recordStatus": 0,
      "TEST_CASE_ID": 3245,
      "TEST_CASE_NAME": "Auto Rate Reset tc",
      "KEY_WORD_ID": 4,
      "KEY_WORD_NAME": "ClickButton",
      "OBJECT_HAPPY_NAME": "AUTO_ RATE_RESET_LOAD_BTN",
      "OBJECT_ID": 27505,
      "OBJECT_TYPE": "AUTO_ RATE_RESET",
      "QUICK_ACCESS": "swfname:=_runButton",
      "ENUM_TYPE": null,
      "APPLICATION_ID": 1,
      "OBJECT_NAME_ID": 27438,
      "TYPE_NAME": "SwfButton",
      "STEPS_ID": 288161,
      "COLUMN_ROW_SETTING": null,
      "COMMENTINFO": null,
      "IS_RUNNABLE": 0,
      "RUN_ORDER": 6,
      "VALUE_SETTING": null
    },
    {
      "dataForDataSets": [
        {
          "Data_Setting_Id": 280698,
          "DATASETVALUE": null,
          "DATA_SUMMARY_ID": 288014,
          "SKIP": 0,
          "STEPS_ID": 288161
        }
      ],
      "recordStatus": 0,
      "TEST_CASE_ID": 3245,
      "TEST_CASE_NAME": "Auto Rate Reset tc",
      "KEY_WORD_ID": 4,
      "KEY_WORD_NAME": "ClickButton",
      "OBJECT_HAPPY_NAME": "AUTO_ RATE_RESET_LOAD_BTN",
      "OBJECT_ID": 41237,
      "OBJECT_TYPE": "AUTO_ RATE_RESET",
      "QUICK_ACCESS": "swfname:=_runButton",
      "ENUM_TYPE": null,
      "APPLICATION_ID": 234,
      "OBJECT_NAME_ID": 27438,
      "TYPE_NAME": "SwfButton",
      "STEPS_ID": 288161,
      "COLUMN_ROW_SETTING": null,
      "COMMENTINFO": null,
      "IS_RUNNABLE": 0,
      "RUN_ORDER": 6,
      "VALUE_SETTING": null
    },
    {
      "dataForDataSets": [
        {
          "Data_Setting_Id": 280698,
          "DATASETVALUE": null,
          "DATA_SUMMARY_ID": 288014,
          "SKIP": 0,
          "STEPS_ID": 288161
        }
      ],
      "recordStatus": 0,
      "TEST_CASE_ID": 3245,
      "TEST_CASE_NAME": "Auto Rate Reset tc",
      "KEY_WORD_ID": 4,
      "KEY_WORD_NAME": "ClickButton",
      "OBJECT_HAPPY_NAME": "AUTO_ RATE_RESET_LOAD_BTN",
      "OBJECT_ID": 48635,
      "OBJECT_TYPE": "AUTO_ RATE_RESET",
      "QUICK_ACCESS": "swfname:=_runButton",
      "ENUM_TYPE": null,
      "APPLICATION_ID": 293,
      "OBJECT_NAME_ID": 27438,
      "TYPE_NAME": "SwfButton",
      "STEPS_ID": 288161,
      "COLUMN_ROW_SETTING": null,
      "COMMENTINFO": null,
      "IS_RUNNABLE": 0,
      "RUN_ORDER": 6,
      "VALUE_SETTING": null
    },
    {
      "dataForDataSets": [
        {
          "Data_Setting_Id": 280699,
          "DATASETVALUE": "Interest Rates",
          "DATA_SUMMARY_ID": 288014,
          "SKIP": 0,
          "STEPS_ID": 288219
        }
      ],
      "recordStatus": 0,
      "TEST_CASE_ID": 3245,
      "TEST_CASE_NAME": "Auto Rate Reset tc",
      "KEY_WORD_ID": 24,
      "KEY_WORD_NAME": "SelectTab",
      "OBJECT_HAPPY_NAME": "AUTO_ RATE_RESET_RESET_RATE_EDIT",
      "OBJECT_ID": 27493,
      "OBJECT_TYPE": "AUTO_ RATE_RESET",
      "QUICK_ACCESS": "swfname:=tabControl1",
      "ENUM_TYPE": null,
      "APPLICATION_ID": 1,
      "OBJECT_NAME_ID": 27451,
      "TYPE_NAME": "swfTab",
      "STEPS_ID": 288219,
      "COLUMN_ROW_SETTING": null,
      "COMMENTINFO": null,
      "IS_RUNNABLE": 0,
      "RUN_ORDER": 7,
      "VALUE_SETTING": null
    },
    {
      "dataForDataSets": [
        {
          "Data_Setting_Id": 280699,
          "DATASETVALUE": "Interest Rates",
          "DATA_SUMMARY_ID": 288014,
          "SKIP": 0,
          "STEPS_ID": 288219
        }
      ],
      "recordStatus": 0,
      "TEST_CASE_ID": 3245,
      "TEST_CASE_NAME": "Auto Rate Reset tc",
      "KEY_WORD_ID": 24,
      "KEY_WORD_NAME": "SelectTab",
      "OBJECT_HAPPY_NAME": "AUTO_ RATE_RESET_RESET_RATE_EDIT",
      "OBJECT_ID": 41225,
      "OBJECT_TYPE": "AUTO_ RATE_RESET",
      "QUICK_ACCESS": "swfname:=tabControl1",
      "ENUM_TYPE": null,
      "APPLICATION_ID": 234,
      "OBJECT_NAME_ID": 27451,
      "TYPE_NAME": "swfTab",
      "STEPS_ID": 288219,
      "COLUMN_ROW_SETTING": null,
      "COMMENTINFO": null,
      "IS_RUNNABLE": 0,
      "RUN_ORDER": 7,
      "VALUE_SETTING": null
    },
    {
      "dataForDataSets": [
        {
          "Data_Setting_Id": 280699,
          "DATASETVALUE": "Interest Rates",
          "DATA_SUMMARY_ID": 288014,
          "SKIP": 0,
          "STEPS_ID": 288219
        }
      ],
      "recordStatus": 0,
      "TEST_CASE_ID": 3245,
      "TEST_CASE_NAME": "Auto Rate Reset tc",
      "KEY_WORD_ID": 24,
      "KEY_WORD_NAME": "SelectTab",
      "OBJECT_HAPPY_NAME": "AUTO_ RATE_RESET_RESET_RATE_EDIT",
      "OBJECT_ID": 48623,
      "OBJECT_TYPE": "AUTO_ RATE_RESET",
      "QUICK_ACCESS": "swfname:=tabControl1",
      "ENUM_TYPE": null,
      "APPLICATION_ID": 293,
      "OBJECT_NAME_ID": 27451,
      "TYPE_NAME": "swfTab",
      "STEPS_ID": 288219,
      "COLUMN_ROW_SETTING": null,
      "COMMENTINFO": null,
      "IS_RUNNABLE": 0,
      "RUN_ORDER": 7,
      "VALUE_SETTING": null
    },
    {
      "dataForDataSets": [
        {
          "Data_Setting_Id": 280681,
          "DATASETVALUE": "4",
          "DATA_SUMMARY_ID": 288014,
          "SKIP": 0,
          "STEPS_ID": 288164
        }
      ],
      "recordStatus": 0,
      "TEST_CASE_ID": 3245,
      "TEST_CASE_NAME": "Auto Rate Reset tc",
      "KEY_WORD_ID": 33,
      "KEY_WORD_NAME": "SearchAndUpdateTable",
      "OBJECT_HAPPY_NAME": "AUTO_ RATE_RESET_INTEREST_RATE",
      "OBJECT_ID": 27469,
      "OBJECT_TYPE": "AUTO_ RATE_RESET",
      "QUICK_ACCESS": "swfname:=_ratesSpr",
      "ENUM_TYPE": null,
      "APPLICATION_ID": 1,
      "OBJECT_NAME_ID": 27423,
      "TYPE_NAME": "SwfTable",
      "STEPS_ID": 288164,
      "COLUMN_ROW_SETTING": "2;Weekly;1",
      "COMMENTINFO": null,
      "IS_RUNNABLE": 0,
      "RUN_ORDER": 8,
      "VALUE_SETTING": null
    },
    {
      "dataForDataSets": [
        {
          "Data_Setting_Id": 280681,
          "DATASETVALUE": "4",
          "DATA_SUMMARY_ID": 288014,
          "SKIP": 0,
          "STEPS_ID": 288164
        }
      ],
      "recordStatus": 0,
      "TEST_CASE_ID": 3245,
      "TEST_CASE_NAME": "Auto Rate Reset tc",
      "KEY_WORD_ID": 33,
      "KEY_WORD_NAME": "SearchAndUpdateTable",
      "OBJECT_HAPPY_NAME": "AUTO_ RATE_RESET_INTEREST_RATE",
      "OBJECT_ID": 41183,
      "OBJECT_TYPE": "AUTO_ RATE_RESET",
      "QUICK_ACCESS": "swfname:=_ratesSpr",
      "ENUM_TYPE": null,
      "APPLICATION_ID": 234,
      "OBJECT_NAME_ID": 27423,
      "TYPE_NAME": "SwfTable",
      "STEPS_ID": 288164,
      "COLUMN_ROW_SETTING": "2;Weekly;1",
      "COMMENTINFO": null,
      "IS_RUNNABLE": 0,
      "RUN_ORDER": 8,
      "VALUE_SETTING": null
    },
    {
      "dataForDataSets": [
        {
          "Data_Setting_Id": 280681,
          "DATASETVALUE": "4",
          "DATA_SUMMARY_ID": 288014,
          "SKIP": 0,
          "STEPS_ID": 288164
        }
      ],
      "recordStatus": 0,
      "TEST_CASE_ID": 3245,
      "TEST_CASE_NAME": "Auto Rate Reset tc",
      "KEY_WORD_ID": 33,
      "KEY_WORD_NAME": "SearchAndUpdateTable",
      "OBJECT_HAPPY_NAME": "AUTO_ RATE_RESET_INTEREST_RATE",
      "OBJECT_ID": 48581,
      "OBJECT_TYPE": "AUTO_ RATE_RESET",
      "QUICK_ACCESS": "swfname:=_ratesSpr",
      "ENUM_TYPE": null,
      "APPLICATION_ID": 293,
      "OBJECT_NAME_ID": 27423,
      "TYPE_NAME": "SwfTable",
      "STEPS_ID": 288164,
      "COLUMN_ROW_SETTING": "2;Weekly;1",
      "COMMENTINFO": null,
      "IS_RUNNABLE": 0,
      "RUN_ORDER": 8,
      "VALUE_SETTING": null
    },
    {
      "dataForDataSets": [
        {
          "Data_Setting_Id": 280695,
          "DATASETVALUE": "1.0",
          "DATA_SUMMARY_ID": 288014,
          "SKIP": 0,
          "STEPS_ID": 288163
        }
      ],
      "recordStatus": 0,
      "TEST_CASE_ID": 3245,
      "TEST_CASE_NAME": "Auto Rate Reset tc",
      "KEY_WORD_ID": 33,
      "KEY_WORD_NAME": "SearchAndUpdateTable",
      "OBJECT_HAPPY_NAME": "AUTO_ RATE_RESET_INTEREST_RATE",
      "OBJECT_ID": 27469,
      "OBJECT_TYPE": "AUTO_ RATE_RESET",
      "QUICK_ACCESS": "swfname:=_ratesSpr",
      "ENUM_TYPE": null,
      "APPLICATION_ID": 1,
      "OBJECT_NAME_ID": 27423,
      "TYPE_NAME": "SwfTable",
      "STEPS_ID": 288163,
      "COLUMN_ROW_SETTING": "2;Monthly;1",
      "COMMENTINFO": null,
      "IS_RUNNABLE": 0,
      "RUN_ORDER": 9,
      "VALUE_SETTING": null
    },
    {
      "dataForDataSets": [
        {
          "Data_Setting_Id": 280695,
          "DATASETVALUE": "1.0",
          "DATA_SUMMARY_ID": 288014,
          "SKIP": 0,
          "STEPS_ID": 288163
        }
      ],
      "recordStatus": 0,
      "TEST_CASE_ID": 3245,
      "TEST_CASE_NAME": "Auto Rate Reset tc",
      "KEY_WORD_ID": 33,
      "KEY_WORD_NAME": "SearchAndUpdateTable",
      "OBJECT_HAPPY_NAME": "AUTO_ RATE_RESET_INTEREST_RATE",
      "OBJECT_ID": 41183,
      "OBJECT_TYPE": "AUTO_ RATE_RESET",
      "QUICK_ACCESS": "swfname:=_ratesSpr",
      "ENUM_TYPE": null,
      "APPLICATION_ID": 234,
      "OBJECT_NAME_ID": 27423,
      "TYPE_NAME": "SwfTable",
      "STEPS_ID": 288163,
      "COLUMN_ROW_SETTING": "2;Monthly;1",
      "COMMENTINFO": null,
      "IS_RUNNABLE": 0,
      "RUN_ORDER": 9,
      "VALUE_SETTING": null
    },
    {
      "dataForDataSets": [
        {
          "Data_Setting_Id": 280695,
          "DATASETVALUE": "1.0",
          "DATA_SUMMARY_ID": 288014,
          "SKIP": 0,
          "STEPS_ID": 288163
        }
      ],
      "recordStatus": 0,
      "TEST_CASE_ID": 3245,
      "TEST_CASE_NAME": "Auto Rate Reset tc",
      "KEY_WORD_ID": 33,
      "KEY_WORD_NAME": "SearchAndUpdateTable",
      "OBJECT_HAPPY_NAME": "AUTO_ RATE_RESET_INTEREST_RATE",
      "OBJECT_ID": 48581,
      "OBJECT_TYPE": "AUTO_ RATE_RESET",
      "QUICK_ACCESS": "swfname:=_ratesSpr",
      "ENUM_TYPE": null,
      "APPLICATION_ID": 293,
      "OBJECT_NAME_ID": 27423,
      "TYPE_NAME": "SwfTable",
      "STEPS_ID": 288163,
      "COLUMN_ROW_SETTING": "2;Monthly;1",
      "COMMENTINFO": null,
      "IS_RUNNABLE": 0,
      "RUN_ORDER": 9,
      "VALUE_SETTING": null
    },
    {
      "dataForDataSets": [
        {
          "Data_Setting_Id": 280677,
          "DATASETVALUE": "0.3",
          "DATA_SUMMARY_ID": 288014,
          "SKIP": 0,
          "STEPS_ID": 288158
        }
      ],
      "recordStatus": 0,
      "TEST_CASE_ID": 3245,
      "TEST_CASE_NAME": "Auto Rate Reset tc",
      "KEY_WORD_ID": 33,
      "KEY_WORD_NAME": "SearchAndUpdateTable",
      "OBJECT_HAPPY_NAME": "AUTO_ RATE_RESET_INTEREST_RATE",
      "OBJECT_ID": 27469,
      "OBJECT_TYPE": "AUTO_ RATE_RESET",
      "QUICK_ACCESS": "swfname:=_ratesSpr",
      "ENUM_TYPE": null,
      "APPLICATION_ID": 1,
      "OBJECT_NAME_ID": 27423,
      "TYPE_NAME": "SwfTable",
      "STEPS_ID": 288158,
      "COLUMN_ROW_SETTING": "2;3M;1",
      "COMMENTINFO": null,
      "IS_RUNNABLE": 0,
      "RUN_ORDER": 10,
      "VALUE_SETTING": null
    },
    {
      "dataForDataSets": [
        {
          "Data_Setting_Id": 280677,
          "DATASETVALUE": "0.3",
          "DATA_SUMMARY_ID": 288014,
          "SKIP": 0,
          "STEPS_ID": 288158
        }
      ],
      "recordStatus": 0,
      "TEST_CASE_ID": 3245,
      "TEST_CASE_NAME": "Auto Rate Reset tc",
      "KEY_WORD_ID": 33,
      "KEY_WORD_NAME": "SearchAndUpdateTable",
      "OBJECT_HAPPY_NAME": "AUTO_ RATE_RESET_INTEREST_RATE",
      "OBJECT_ID": 41183,
      "OBJECT_TYPE": "AUTO_ RATE_RESET",
      "QUICK_ACCESS": "swfname:=_ratesSpr",
      "ENUM_TYPE": null,
      "APPLICATION_ID": 234,
      "OBJECT_NAME_ID": 27423,
      "TYPE_NAME": "SwfTable",
      "STEPS_ID": 288158,
      "COLUMN_ROW_SETTING": "2;3M;1",
      "COMMENTINFO": null,
      "IS_RUNNABLE": 0,
      "RUN_ORDER": 10,
      "VALUE_SETTING": null
    },
    {
      "dataForDataSets": [
        {
          "Data_Setting_Id": 280677,
          "DATASETVALUE": "0.3",
          "DATA_SUMMARY_ID": 288014,
          "SKIP": 0,
          "STEPS_ID": 288158
        }
      ],
      "recordStatus": 0,
      "TEST_CASE_ID": 3245,
      "TEST_CASE_NAME": "Auto Rate Reset tc",
      "KEY_WORD_ID": 33,
      "KEY_WORD_NAME": "SearchAndUpdateTable",
      "OBJECT_HAPPY_NAME": "AUTO_ RATE_RESET_INTEREST_RATE",
      "OBJECT_ID": 48581,
      "OBJECT_TYPE": "AUTO_ RATE_RESET",
      "QUICK_ACCESS": "swfname:=_ratesSpr",
      "ENUM_TYPE": null,
      "APPLICATION_ID": 293,
      "OBJECT_NAME_ID": 27423,
      "TYPE_NAME": "SwfTable",
      "STEPS_ID": 288158,
      "COLUMN_ROW_SETTING": "2;3M;1",
      "COMMENTINFO": null,
      "IS_RUNNABLE": 0,
      "RUN_ORDER": 10,
      "VALUE_SETTING": null
    },
    {
      "dataForDataSets": [
        {
          "Data_Setting_Id": 280680,
          "DATASETVALUE": "0.6",
          "DATA_SUMMARY_ID": 288014,
          "SKIP": 0,
          "STEPS_ID": 288162
        }
      ],
      "recordStatus": 0,
      "TEST_CASE_ID": 3245,
      "TEST_CASE_NAME": "Auto Rate Reset tc",
      "KEY_WORD_ID": 33,
      "KEY_WORD_NAME": "SearchAndUpdateTable",
      "OBJECT_HAPPY_NAME": "AUTO_ RATE_RESET_INTEREST_RATE",
      "OBJECT_ID": 27469,
      "OBJECT_TYPE": "AUTO_ RATE_RESET",
      "QUICK_ACCESS": "swfname:=_ratesSpr",
      "ENUM_TYPE": null,
      "APPLICATION_ID": 1,
      "OBJECT_NAME_ID": 27423,
      "TYPE_NAME": "SwfTable",
      "STEPS_ID": 288162,
      "COLUMN_ROW_SETTING": "2;6M;1",
      "COMMENTINFO": null,
      "IS_RUNNABLE": 0,
      "RUN_ORDER": 11,
      "VALUE_SETTING": null
    },
    {
      "dataForDataSets": [
        {
          "Data_Setting_Id": 280680,
          "DATASETVALUE": "0.6",
          "DATA_SUMMARY_ID": 288014,
          "SKIP": 0,
          "STEPS_ID": 288162
        }
      ],
      "recordStatus": 0,
      "TEST_CASE_ID": 3245,
      "TEST_CASE_NAME": "Auto Rate Reset tc",
      "KEY_WORD_ID": 33,
      "KEY_WORD_NAME": "SearchAndUpdateTable",
      "OBJECT_HAPPY_NAME": "AUTO_ RATE_RESET_INTEREST_RATE",
      "OBJECT_ID": 41183,
      "OBJECT_TYPE": "AUTO_ RATE_RESET",
      "QUICK_ACCESS": "swfname:=_ratesSpr",
      "ENUM_TYPE": null,
      "APPLICATION_ID": 234,
      "OBJECT_NAME_ID": 27423,
      "TYPE_NAME": "SwfTable",
      "STEPS_ID": 288162,
      "COLUMN_ROW_SETTING": "2;6M;1",
      "COMMENTINFO": null,
      "IS_RUNNABLE": 0,
      "RUN_ORDER": 11,
      "VALUE_SETTING": null
    },
    {
      "dataForDataSets": [
        {
          "Data_Setting_Id": 280680,
          "DATASETVALUE": "0.6",
          "DATA_SUMMARY_ID": 288014,
          "SKIP": 0,
          "STEPS_ID": 288162
        }
      ],
      "recordStatus": 0,
      "TEST_CASE_ID": 3245,
      "TEST_CASE_NAME": "Auto Rate Reset tc",
      "KEY_WORD_ID": 33,
      "KEY_WORD_NAME": "SearchAndUpdateTable",
      "OBJECT_HAPPY_NAME": "AUTO_ RATE_RESET_INTEREST_RATE",
      "OBJECT_ID": 48581,
      "OBJECT_TYPE": "AUTO_ RATE_RESET",
      "QUICK_ACCESS": "swfname:=_ratesSpr",
      "ENUM_TYPE": null,
      "APPLICATION_ID": 293,
      "OBJECT_NAME_ID": 27423,
      "TYPE_NAME": "SwfTable",
      "STEPS_ID": 288162,
      "COLUMN_ROW_SETTING": "2;6M;1",
      "COMMENTINFO": null,
      "IS_RUNNABLE": 0,
      "RUN_ORDER": 11,
      "VALUE_SETTING": null
    },
    {
      "dataForDataSets": [
        {
          "Data_Setting_Id": 280691,
          "DATASETVALUE": "0.12",
          "DATA_SUMMARY_ID": 288014,
          "SKIP": 0,
          "STEPS_ID": 288174
        }
      ],
      "recordStatus": 0,
      "TEST_CASE_ID": 3245,
      "TEST_CASE_NAME": "Auto Rate Reset tc",
      "KEY_WORD_ID": 33,
      "KEY_WORD_NAME": "SearchAndUpdateTable",
      "OBJECT_HAPPY_NAME": "AUTO_ RATE_RESET_INTEREST_RATE",
      "OBJECT_ID": 27469,
      "OBJECT_TYPE": "AUTO_ RATE_RESET",
      "QUICK_ACCESS": "swfname:=_ratesSpr",
      "ENUM_TYPE": null,
      "APPLICATION_ID": 1,
      "OBJECT_NAME_ID": 27423,
      "TYPE_NAME": "SwfTable",
      "STEPS_ID": 288174,
      "COLUMN_ROW_SETTING": "2;1Y;1",
      "COMMENTINFO": null,
      "IS_RUNNABLE": 0,
      "RUN_ORDER": 12,
      "VALUE_SETTING": null
    },
    {
      "dataForDataSets": [
        {
          "Data_Setting_Id": 280691,
          "DATASETVALUE": "0.12",
          "DATA_SUMMARY_ID": 288014,
          "SKIP": 0,
          "STEPS_ID": 288174
        }
      ],
      "recordStatus": 0,
      "TEST_CASE_ID": 3245,
      "TEST_CASE_NAME": "Auto Rate Reset tc",
      "KEY_WORD_ID": 33,
      "KEY_WORD_NAME": "SearchAndUpdateTable",
      "OBJECT_HAPPY_NAME": "AUTO_ RATE_RESET_INTEREST_RATE",
      "OBJECT_ID": 41183,
      "OBJECT_TYPE": "AUTO_ RATE_RESET",
      "QUICK_ACCESS": "swfname:=_ratesSpr",
      "ENUM_TYPE": null,
      "APPLICATION_ID": 234,
      "OBJECT_NAME_ID": 27423,
      "TYPE_NAME": "SwfTable",
      "STEPS_ID": 288174,
      "COLUMN_ROW_SETTING": "2;1Y;1",
      "COMMENTINFO": null,
      "IS_RUNNABLE": 0,
      "RUN_ORDER": 12,
      "VALUE_SETTING": null
    },
    {
      "dataForDataSets": [
        {
          "Data_Setting_Id": 280691,
          "DATASETVALUE": "0.12",
          "DATA_SUMMARY_ID": 288014,
          "SKIP": 0,
          "STEPS_ID": 288174
        }
      ],
      "recordStatus": 0,
      "TEST_CASE_ID": 3245,
      "TEST_CASE_NAME": "Auto Rate Reset tc",
      "KEY_WORD_ID": 33,
      "KEY_WORD_NAME": "SearchAndUpdateTable",
      "OBJECT_HAPPY_NAME": "AUTO_ RATE_RESET_INTEREST_RATE",
      "OBJECT_ID": 48581,
      "OBJECT_TYPE": "AUTO_ RATE_RESET",
      "QUICK_ACCESS": "swfname:=_ratesSpr",
      "ENUM_TYPE": null,
      "APPLICATION_ID": 293,
      "OBJECT_NAME_ID": 27423,
      "TYPE_NAME": "SwfTable",
      "STEPS_ID": 288174,
      "COLUMN_ROW_SETTING": "2;1Y;1",
      "COMMENTINFO": null,
      "IS_RUNNABLE": 0,
      "RUN_ORDER": 12,
      "VALUE_SETTING": null
    },
    {
      "dataForDataSets": [
        {
          "Data_Setting_Id": 280696,
          "DATASETVALUE": "FX Rates",
          "DATA_SUMMARY_ID": 288014,
          "SKIP": 0,
          "STEPS_ID": 288197
        }
      ],
      "recordStatus": 0,
      "TEST_CASE_ID": 3245,
      "TEST_CASE_NAME": "Auto Rate Reset tc",
      "KEY_WORD_ID": 24,
      "KEY_WORD_NAME": "SelectTab",
      "OBJECT_HAPPY_NAME": "AUTO_ RATE_RESET_RESET_RATE_EDIT",
      "OBJECT_ID": 27493,
      "OBJECT_TYPE": "AUTO_ RATE_RESET",
      "QUICK_ACCESS": "swfname:=tabControl1",
      "ENUM_TYPE": null,
      "APPLICATION_ID": 1,
      "OBJECT_NAME_ID": 27451,
      "TYPE_NAME": "swfTab",
      "STEPS_ID": 288197,
      "COLUMN_ROW_SETTING": null,
      "COMMENTINFO": null,
      "IS_RUNNABLE": 0,
      "RUN_ORDER": 13,
      "VALUE_SETTING": null
    },
    {
      "dataForDataSets": [
        {
          "Data_Setting_Id": 280696,
          "DATASETVALUE": "FX Rates",
          "DATA_SUMMARY_ID": 288014,
          "SKIP": 0,
          "STEPS_ID": 288197
        }
      ],
      "recordStatus": 0,
      "TEST_CASE_ID": 3245,
      "TEST_CASE_NAME": "Auto Rate Reset tc",
      "KEY_WORD_ID": 24,
      "KEY_WORD_NAME": "SelectTab",
      "OBJECT_HAPPY_NAME": "AUTO_ RATE_RESET_RESET_RATE_EDIT",
      "OBJECT_ID": 41225,
      "OBJECT_TYPE": "AUTO_ RATE_RESET",
      "QUICK_ACCESS": "swfname:=tabControl1",
      "ENUM_TYPE": null,
      "APPLICATION_ID": 234,
      "OBJECT_NAME_ID": 27451,
      "TYPE_NAME": "swfTab",
      "STEPS_ID": 288197,
      "COLUMN_ROW_SETTING": null,
      "COMMENTINFO": null,
      "IS_RUNNABLE": 0,
      "RUN_ORDER": 13,
      "VALUE_SETTING": null
    },
    {
      "dataForDataSets": [
        {
          "Data_Setting_Id": 280696,
          "DATASETVALUE": "FX Rates",
          "DATA_SUMMARY_ID": 288014,
          "SKIP": 0,
          "STEPS_ID": 288197
        }
      ],
      "recordStatus": 0,
      "TEST_CASE_ID": 3245,
      "TEST_CASE_NAME": "Auto Rate Reset tc",
      "KEY_WORD_ID": 24,
      "KEY_WORD_NAME": "SelectTab",
      "OBJECT_HAPPY_NAME": "AUTO_ RATE_RESET_RESET_RATE_EDIT",
      "OBJECT_ID": 48623,
      "OBJECT_TYPE": "AUTO_ RATE_RESET",
      "QUICK_ACCESS": "swfname:=tabControl1",
      "ENUM_TYPE": null,
      "APPLICATION_ID": 293,
      "OBJECT_NAME_ID": 27451,
      "TYPE_NAME": "swfTab",
      "STEPS_ID": 288197,
      "COLUMN_ROW_SETTING": null,
      "COMMENTINFO": null,
      "IS_RUNNABLE": 0,
      "RUN_ORDER": 13,
      "VALUE_SETTING": null
    },
    {
      "dataForDataSets": [
        {
          "Data_Setting_Id": 280692,
          "DATASETVALUE": "400",
          "DATA_SUMMARY_ID": 288014,
          "SKIP": 0,
          "STEPS_ID": 288175
        }
      ],
      "recordStatus": 0,
      "TEST_CASE_ID": 3245,
      "TEST_CASE_NAME": "Auto Rate Reset tc",
      "KEY_WORD_ID": 33,
      "KEY_WORD_NAME": "SearchAndUpdateTable",
      "OBJECT_HAPPY_NAME": "AUTO_ RATE_RESET_FX_RATES",
      "OBJECT_ID": 27479,
      "OBJECT_TYPE": "AUTO_ RATE_RESET",
      "QUICK_ACCESS": "swfname:=_fxRatesSpr",
      "ENUM_TYPE": null,
      "APPLICATION_ID": 1,
      "OBJECT_NAME_ID": 27440,
      "TYPE_NAME": "SwfTable",
      "STEPS_ID": 288175,
      "COLUMN_ROW_SETTING": "2;spot;1",
      "COMMENTINFO": null,
      "IS_RUNNABLE": 0,
      "RUN_ORDER": 14,
      "VALUE_SETTING": null
    },
    {
      "dataForDataSets": [
        {
          "Data_Setting_Id": 280692,
          "DATASETVALUE": "400",
          "DATA_SUMMARY_ID": 288014,
          "SKIP": 0,
          "STEPS_ID": 288175
        }
      ],
      "recordStatus": 0,
      "TEST_CASE_ID": 3245,
      "TEST_CASE_NAME": "Auto Rate Reset tc",
      "KEY_WORD_ID": 33,
      "KEY_WORD_NAME": "SearchAndUpdateTable",
      "OBJECT_HAPPY_NAME": "AUTO_ RATE_RESET_FX_RATES",
      "OBJECT_ID": 41193,
      "OBJECT_TYPE": "AUTO_ RATE_RESET",
      "QUICK_ACCESS": "swfname:=_fxRatesSpr",
      "ENUM_TYPE": null,
      "APPLICATION_ID": 234,
      "OBJECT_NAME_ID": 27440,
      "TYPE_NAME": "SwfTable",
      "STEPS_ID": 288175,
      "COLUMN_ROW_SETTING": "2;spot;1",
      "COMMENTINFO": null,
      "IS_RUNNABLE": 0,
      "RUN_ORDER": 14,
      "VALUE_SETTING": null
    },
    {
      "dataForDataSets": [
        {
          "Data_Setting_Id": 280692,
          "DATASETVALUE": "400",
          "DATA_SUMMARY_ID": 288014,
          "SKIP": 0,
          "STEPS_ID": 288175
        }
      ],
      "recordStatus": 0,
      "TEST_CASE_ID": 3245,
      "TEST_CASE_NAME": "Auto Rate Reset tc",
      "KEY_WORD_ID": 33,
      "KEY_WORD_NAME": "SearchAndUpdateTable",
      "OBJECT_HAPPY_NAME": "AUTO_ RATE_RESET_FX_RATES",
      "OBJECT_ID": 48591,
      "OBJECT_TYPE": "AUTO_ RATE_RESET",
      "QUICK_ACCESS": "swfname:=_fxRatesSpr",
      "ENUM_TYPE": null,
      "APPLICATION_ID": 293,
      "OBJECT_NAME_ID": 27440,
      "TYPE_NAME": "SwfTable",
      "STEPS_ID": 288175,
      "COLUMN_ROW_SETTING": "2;spot;1",
      "COMMENTINFO": null,
      "IS_RUNNABLE": 0,
      "RUN_ORDER": 14,
      "VALUE_SETTING": null
    },
    {
      "dataForDataSets": [
        {
          "Data_Setting_Id": 280689,
          "DATASETVALUE": "2000",
          "DATA_SUMMARY_ID": 288014,
          "SKIP": 0,
          "STEPS_ID": 288172
        }
      ],
      "recordStatus": 0,
      "TEST_CASE_ID": 3245,
      "TEST_CASE_NAME": "Auto Rate Reset tc",
      "KEY_WORD_ID": 33,
      "KEY_WORD_NAME": "SearchAndUpdateTable",
      "OBJECT_HAPPY_NAME": "AUTO_ RATE_RESET_FX_RATES",
      "OBJECT_ID": 27479,
      "OBJECT_TYPE": "AUTO_ RATE_RESET",
      "QUICK_ACCESS": "swfname:=_fxRatesSpr",
      "ENUM_TYPE": null,
      "APPLICATION_ID": 1,
      "OBJECT_NAME_ID": 27440,
      "TYPE_NAME": "SwfTable",
      "STEPS_ID": 288172,
      "COLUMN_ROW_SETTING": "3;spot;1",
      "COMMENTINFO": null,
      "IS_RUNNABLE": 0,
      "RUN_ORDER": 15,
      "VALUE_SETTING": null
    },
    {
      "dataForDataSets": [
        {
          "Data_Setting_Id": 280689,
          "DATASETVALUE": "2000",
          "DATA_SUMMARY_ID": 288014,
          "SKIP": 0,
          "STEPS_ID": 288172
        }
      ],
      "recordStatus": 0,
      "TEST_CASE_ID": 3245,
      "TEST_CASE_NAME": "Auto Rate Reset tc",
      "KEY_WORD_ID": 33,
      "KEY_WORD_NAME": "SearchAndUpdateTable",
      "OBJECT_HAPPY_NAME": "AUTO_ RATE_RESET_FX_RATES",
      "OBJECT_ID": 41193,
      "OBJECT_TYPE": "AUTO_ RATE_RESET",
      "QUICK_ACCESS": "swfname:=_fxRatesSpr",
      "ENUM_TYPE": null,
      "APPLICATION_ID": 234,
      "OBJECT_NAME_ID": 27440,
      "TYPE_NAME": "SwfTable",
      "STEPS_ID": 288172,
      "COLUMN_ROW_SETTING": "3;spot;1",
      "COMMENTINFO": null,
      "IS_RUNNABLE": 0,
      "RUN_ORDER": 15,
      "VALUE_SETTING": null
    },
    {
      "dataForDataSets": [
        {
          "Data_Setting_Id": 280689,
          "DATASETVALUE": "2000",
          "DATA_SUMMARY_ID": 288014,
          "SKIP": 0,
          "STEPS_ID": 288172
        }
      ],
      "recordStatus": 0,
      "TEST_CASE_ID": 3245,
      "TEST_CASE_NAME": "Auto Rate Reset tc",
      "KEY_WORD_ID": 33,
      "KEY_WORD_NAME": "SearchAndUpdateTable",
      "OBJECT_HAPPY_NAME": "AUTO_ RATE_RESET_FX_RATES",
      "OBJECT_ID": 48591,
      "OBJECT_TYPE": "AUTO_ RATE_RESET",
      "QUICK_ACCESS": "swfname:=_fxRatesSpr",
      "ENUM_TYPE": null,
      "APPLICATION_ID": 293,
      "OBJECT_NAME_ID": 27440,
      "TYPE_NAME": "SwfTable",
      "STEPS_ID": 288172,
      "COLUMN_ROW_SETTING": "3;spot;1",
      "COMMENTINFO": null,
      "IS_RUNNABLE": 0,
      "RUN_ORDER": 15,
      "VALUE_SETTING": null
    },
    {
      "dataForDataSets": [
        {
          "Data_Setting_Id": 280678,
          "DATASETVALUE": "Equity Prices",
          "DATA_SUMMARY_ID": 288014,
          "SKIP": 0,
          "STEPS_ID": 288159
        }
      ],
      "recordStatus": 0,
      "TEST_CASE_ID": 3245,
      "TEST_CASE_NAME": "Auto Rate Reset tc",
      "KEY_WORD_ID": 24,
      "KEY_WORD_NAME": "SelectTab",
      "OBJECT_HAPPY_NAME": "AUTO_ RATE_RESET_RESET_RATE_EDIT",
      "OBJECT_ID": 27493,
      "OBJECT_TYPE": "AUTO_ RATE_RESET",
      "QUICK_ACCESS": "swfname:=tabControl1",
      "ENUM_TYPE": null,
      "APPLICATION_ID": 1,
      "OBJECT_NAME_ID": 27451,
      "TYPE_NAME": "swfTab",
      "STEPS_ID": 288159,
      "COLUMN_ROW_SETTING": null,
      "COMMENTINFO": null,
      "IS_RUNNABLE": 0,
      "RUN_ORDER": 16,
      "VALUE_SETTING": null
    },
    {
      "dataForDataSets": [
        {
          "Data_Setting_Id": 280678,
          "DATASETVALUE": "Equity Prices",
          "DATA_SUMMARY_ID": 288014,
          "SKIP": 0,
          "STEPS_ID": 288159
        }
      ],
      "recordStatus": 0,
      "TEST_CASE_ID": 3245,
      "TEST_CASE_NAME": "Auto Rate Reset tc",
      "KEY_WORD_ID": 24,
      "KEY_WORD_NAME": "SelectTab",
      "OBJECT_HAPPY_NAME": "AUTO_ RATE_RESET_RESET_RATE_EDIT",
      "OBJECT_ID": 41225,
      "OBJECT_TYPE": "AUTO_ RATE_RESET",
      "QUICK_ACCESS": "swfname:=tabControl1",
      "ENUM_TYPE": null,
      "APPLICATION_ID": 234,
      "OBJECT_NAME_ID": 27451,
      "TYPE_NAME": "swfTab",
      "STEPS_ID": 288159,
      "COLUMN_ROW_SETTING": null,
      "COMMENTINFO": null,
      "IS_RUNNABLE": 0,
      "RUN_ORDER": 16,
      "VALUE_SETTING": null
    },
    {
      "dataForDataSets": [
        {
          "Data_Setting_Id": 280678,
          "DATASETVALUE": "Equity Prices",
          "DATA_SUMMARY_ID": 288014,
          "SKIP": 0,
          "STEPS_ID": 288159
        }
      ],
      "recordStatus": 0,
      "TEST_CASE_ID": 3245,
      "TEST_CASE_NAME": "Auto Rate Reset tc",
      "KEY_WORD_ID": 24,
      "KEY_WORD_NAME": "SelectTab",
      "OBJECT_HAPPY_NAME": "AUTO_ RATE_RESET_RESET_RATE_EDIT",
      "OBJECT_ID": 48623,
      "OBJECT_TYPE": "AUTO_ RATE_RESET",
      "QUICK_ACCESS": "swfname:=tabControl1",
      "ENUM_TYPE": null,
      "APPLICATION_ID": 293,
      "OBJECT_NAME_ID": 27451,
      "TYPE_NAME": "swfTab",
      "STEPS_ID": 288159,
      "COLUMN_ROW_SETTING": null,
      "COMMENTINFO": null,
      "IS_RUNNABLE": 0,
      "RUN_ORDER": 16,
      "VALUE_SETTING": null
    },
    {
      "dataForDataSets": [
        {
          "Data_Setting_Id": 280684,
          "DATASETVALUE": "4000",
          "DATA_SUMMARY_ID": 288014,
          "SKIP": 0,
          "STEPS_ID": 288167
        }
      ],
      "recordStatus": 0,
      "TEST_CASE_ID": 3245,
      "TEST_CASE_NAME": "Auto Rate Reset tc",
      "KEY_WORD_ID": 33,
      "KEY_WORD_NAME": "SearchAndUpdateTable",
      "OBJECT_HAPPY_NAME": "AUTO_ RATE_RESET_EQUITY_PRICES",
      "OBJECT_ID": 27470,
      "OBJECT_TYPE": "AUTO_ RATE_RESET",
      "QUICK_ACCESS": "swfname:=_equitySpr",
      "ENUM_TYPE": null,
      "APPLICATION_ID": 1,
      "OBJECT_NAME_ID": 27424,
      "TYPE_NAME": "SwfTable",
      "STEPS_ID": 288167,
      "COLUMN_ROW_SETTING": "1;Price;1",
      "COMMENTINFO": null,
      "IS_RUNNABLE": 0,
      "RUN_ORDER": 17,
      "VALUE_SETTING": null
    },
    {
      "dataForDataSets": [
        {
          "Data_Setting_Id": 280684,
          "DATASETVALUE": "4000",
          "DATA_SUMMARY_ID": 288014,
          "SKIP": 0,
          "STEPS_ID": 288167
        }
      ],
      "recordStatus": 0,
      "TEST_CASE_ID": 3245,
      "TEST_CASE_NAME": "Auto Rate Reset tc",
      "KEY_WORD_ID": 33,
      "KEY_WORD_NAME": "SearchAndUpdateTable",
      "OBJECT_HAPPY_NAME": "AUTO_ RATE_RESET_EQUITY_PRICES",
      "OBJECT_ID": 41184,
      "OBJECT_TYPE": "AUTO_ RATE_RESET",
      "QUICK_ACCESS": "swfname:=_equitySpr",
      "ENUM_TYPE": null,
      "APPLICATION_ID": 234,
      "OBJECT_NAME_ID": 27424,
      "TYPE_NAME": "SwfTable",
      "STEPS_ID": 288167,
      "COLUMN_ROW_SETTING": "1;Price;1",
      "COMMENTINFO": null,
      "IS_RUNNABLE": 0,
      "RUN_ORDER": 17,
      "VALUE_SETTING": null
    },
    {
      "dataForDataSets": [
        {
          "Data_Setting_Id": 280684,
          "DATASETVALUE": "4000",
          "DATA_SUMMARY_ID": 288014,
          "SKIP": 0,
          "STEPS_ID": 288167
        }
      ],
      "recordStatus": 0,
      "TEST_CASE_ID": 3245,
      "TEST_CASE_NAME": "Auto Rate Reset tc",
      "KEY_WORD_ID": 33,
      "KEY_WORD_NAME": "SearchAndUpdateTable",
      "OBJECT_HAPPY_NAME": "AUTO_ RATE_RESET_EQUITY_PRICES",
      "OBJECT_ID": 48582,
      "OBJECT_TYPE": "AUTO_ RATE_RESET",
      "QUICK_ACCESS": "swfname:=_equitySpr",
      "ENUM_TYPE": null,
      "APPLICATION_ID": 293,
      "OBJECT_NAME_ID": 27424,
      "TYPE_NAME": "SwfTable",
      "STEPS_ID": 288167,
      "COLUMN_ROW_SETTING": "1;Price;1",
      "COMMENTINFO": null,
      "IS_RUNNABLE": 0,
      "RUN_ORDER": 17,
      "VALUE_SETTING": null
    },
    {
      "dataForDataSets": [
        {
          "Data_Setting_Id": 280693,
          "DATASETVALUE": "Credit Spreads",
          "DATA_SUMMARY_ID": 288014,
          "SKIP": 0,
          "STEPS_ID": 288176
        }
      ],
      "recordStatus": 0,
      "TEST_CASE_ID": 3245,
      "TEST_CASE_NAME": "Auto Rate Reset tc",
      "KEY_WORD_ID": 24,
      "KEY_WORD_NAME": "SelectTab",
      "OBJECT_HAPPY_NAME": "AUTO_ RATE_RESET_RESET_RATE_EDIT",
      "OBJECT_ID": 27493,
      "OBJECT_TYPE": "AUTO_ RATE_RESET",
      "QUICK_ACCESS": "swfname:=tabControl1",
      "ENUM_TYPE": null,
      "APPLICATION_ID": 1,
      "OBJECT_NAME_ID": 27451,
      "TYPE_NAME": "swfTab",
      "STEPS_ID": 288176,
      "COLUMN_ROW_SETTING": null,
      "COMMENTINFO": null,
      "IS_RUNNABLE": 0,
      "RUN_ORDER": 18,
      "VALUE_SETTING": null
    },
    {
      "dataForDataSets": [
        {
          "Data_Setting_Id": 280693,
          "DATASETVALUE": "Credit Spreads",
          "DATA_SUMMARY_ID": 288014,
          "SKIP": 0,
          "STEPS_ID": 288176
        }
      ],
      "recordStatus": 0,
      "TEST_CASE_ID": 3245,
      "TEST_CASE_NAME": "Auto Rate Reset tc",
      "KEY_WORD_ID": 24,
      "KEY_WORD_NAME": "SelectTab",
      "OBJECT_HAPPY_NAME": "AUTO_ RATE_RESET_RESET_RATE_EDIT",
      "OBJECT_ID": 41225,
      "OBJECT_TYPE": "AUTO_ RATE_RESET",
      "QUICK_ACCESS": "swfname:=tabControl1",
      "ENUM_TYPE": null,
      "APPLICATION_ID": 234,
      "OBJECT_NAME_ID": 27451,
      "TYPE_NAME": "swfTab",
      "STEPS_ID": 288176,
      "COLUMN_ROW_SETTING": null,
      "COMMENTINFO": null,
      "IS_RUNNABLE": 0,
      "RUN_ORDER": 18,
      "VALUE_SETTING": null
    },
    {
      "dataForDataSets": [
        {
          "Data_Setting_Id": 280693,
          "DATASETVALUE": "Credit Spreads",
          "DATA_SUMMARY_ID": 288014,
          "SKIP": 0,
          "STEPS_ID": 288176
        }
      ],
      "recordStatus": 0,
      "TEST_CASE_ID": 3245,
      "TEST_CASE_NAME": "Auto Rate Reset tc",
      "KEY_WORD_ID": 24,
      "KEY_WORD_NAME": "SelectTab",
      "OBJECT_HAPPY_NAME": "AUTO_ RATE_RESET_RESET_RATE_EDIT",
      "OBJECT_ID": 48623,
      "OBJECT_TYPE": "AUTO_ RATE_RESET",
      "QUICK_ACCESS": "swfname:=tabControl1",
      "ENUM_TYPE": null,
      "APPLICATION_ID": 293,
      "OBJECT_NAME_ID": 27451,
      "TYPE_NAME": "swfTab",
      "STEPS_ID": 288176,
      "COLUMN_ROW_SETTING": null,
      "COMMENTINFO": null,
      "IS_RUNNABLE": 0,
      "RUN_ORDER": 18,
      "VALUE_SETTING": null
    },
    {
      "dataForDataSets": [
        {
          "Data_Setting_Id": 280685,
          "DATASETVALUE": "Bond Prices",
          "DATA_SUMMARY_ID": 288014,
          "SKIP": 0,
          "STEPS_ID": 288168
        }
      ],
      "recordStatus": 0,
      "TEST_CASE_ID": 3245,
      "TEST_CASE_NAME": "Auto Rate Reset tc",
      "KEY_WORD_ID": 24,
      "KEY_WORD_NAME": "SelectTab",
      "OBJECT_HAPPY_NAME": "AUTO_ RATE_RESET_RESET_RATE_EDIT",
      "OBJECT_ID": 27493,
      "OBJECT_TYPE": "AUTO_ RATE_RESET",
      "QUICK_ACCESS": "swfname:=tabControl1",
      "ENUM_TYPE": null,
      "APPLICATION_ID": 1,
      "OBJECT_NAME_ID": 27451,
      "TYPE_NAME": "swfTab",
      "STEPS_ID": 288168,
      "COLUMN_ROW_SETTING": null,
      "COMMENTINFO": null,
      "IS_RUNNABLE": 0,
      "RUN_ORDER": 19,
      "VALUE_SETTING": null
    },
    {
      "dataForDataSets": [
        {
          "Data_Setting_Id": 280685,
          "DATASETVALUE": "Bond Prices",
          "DATA_SUMMARY_ID": 288014,
          "SKIP": 0,
          "STEPS_ID": 288168
        }
      ],
      "recordStatus": 0,
      "TEST_CASE_ID": 3245,
      "TEST_CASE_NAME": "Auto Rate Reset tc",
      "KEY_WORD_ID": 24,
      "KEY_WORD_NAME": "SelectTab",
      "OBJECT_HAPPY_NAME": "AUTO_ RATE_RESET_RESET_RATE_EDIT",
      "OBJECT_ID": 41225,
      "OBJECT_TYPE": "AUTO_ RATE_RESET",
      "QUICK_ACCESS": "swfname:=tabControl1",
      "ENUM_TYPE": null,
      "APPLICATION_ID": 234,
      "OBJECT_NAME_ID": 27451,
      "TYPE_NAME": "swfTab",
      "STEPS_ID": 288168,
      "COLUMN_ROW_SETTING": null,
      "COMMENTINFO": null,
      "IS_RUNNABLE": 0,
      "RUN_ORDER": 19,
      "VALUE_SETTING": null
    },
    {
      "dataForDataSets": [
        {
          "Data_Setting_Id": 280685,
          "DATASETVALUE": "Bond Prices",
          "DATA_SUMMARY_ID": 288014,
          "SKIP": 0,
          "STEPS_ID": 288168
        }
      ],
      "recordStatus": 0,
      "TEST_CASE_ID": 3245,
      "TEST_CASE_NAME": "Auto Rate Reset tc",
      "KEY_WORD_ID": 24,
      "KEY_WORD_NAME": "SelectTab",
      "OBJECT_HAPPY_NAME": "AUTO_ RATE_RESET_RESET_RATE_EDIT",
      "OBJECT_ID": 48623,
      "OBJECT_TYPE": "AUTO_ RATE_RESET",
      "QUICK_ACCESS": "swfname:=tabControl1",
      "ENUM_TYPE": null,
      "APPLICATION_ID": 293,
      "OBJECT_NAME_ID": 27451,
      "TYPE_NAME": "swfTab",
      "STEPS_ID": 288168,
      "COLUMN_ROW_SETTING": null,
      "COMMENTINFO": null,
      "IS_RUNNABLE": 0,
      "RUN_ORDER": 19,
      "VALUE_SETTING": null
    },
    {
      "dataForDataSets": [
        {
          "Data_Setting_Id": 280682,
          "DATASETVALUE": null,
          "DATA_SUMMARY_ID": 288014,
          "SKIP": 0,
          "STEPS_ID": 288165
        }
      ],
      "recordStatus": 0,
      "TEST_CASE_ID": 3245,
      "TEST_CASE_NAME": "Auto Rate Reset tc",
      "KEY_WORD_ID": 3,
      "KEY_WORD_NAME": "CheckError",
      "OBJECT_HAPPY_NAME": null,
      "OBJECT_ID": -1,
      "OBJECT_TYPE": null,
      "QUICK_ACCESS": null,
      "ENUM_TYPE": null,
      "APPLICATION_ID": -1,
      "OBJECT_NAME_ID": -1,
      "TYPE_NAME": " ",
      "STEPS_ID": 288165,
      "COLUMN_ROW_SETTING": null,
      "COMMENTINFO": null,
      "IS_RUNNABLE": 0,
      "RUN_ORDER": 20,
      "VALUE_SETTING": null
    },
    {
      "dataForDataSets": [
        {
          "Data_Setting_Id": 280688,
          "DATASETVALUE": "5",
          "DATA_SUMMARY_ID": 288014,
          "SKIP": 0,
          "STEPS_ID": 288171
        }
      ],
      "recordStatus": 0,
      "TEST_CASE_ID": 3245,
      "TEST_CASE_NAME": "Auto Rate Reset tc",
      "KEY_WORD_ID": 37,
      "KEY_WORD_NAME": "WaitForSeconds",
      "OBJECT_HAPPY_NAME": null,
      "OBJECT_ID": -1,
      "OBJECT_TYPE": null,
      "QUICK_ACCESS": null,
      "ENUM_TYPE": null,
      "APPLICATION_ID": -1,
      "OBJECT_NAME_ID": -1,
      "TYPE_NAME": " ",
      "STEPS_ID": 288171,
      "COLUMN_ROW_SETTING": null,
      "COMMENTINFO": null,
      "IS_RUNNABLE": 0,
      "RUN_ORDER": 21,
      "VALUE_SETTING": null
    },
    {
      "dataForDataSets": [
        {
          "Data_Setting_Id": 280783,
          "DATASETVALUE": null,
          "DATA_SUMMARY_ID": 288014,
          "SKIP": 0,
          "STEPS_ID": 288544
        }
      ],
      "recordStatus": 0,
      "TEST_CASE_ID": 3245,
      "TEST_CASE_NAME": "Auto Rate Reset tc",
      "KEY_WORD_ID": 15,
      "KEY_WORD_NAME": "PegWindow",
      "OBJECT_HAPPY_NAME": "Summit Start",
      "OBJECT_ID": 38857,
      "OBJECT_TYPE": "Summit Start",
      "QUICK_ACCESS": "is owned window:=False\r\nis child window:=False\r\ntext:=((Misys|Finastra ){0,1}(FusionCapital|Fusion ){0,1}(Markets ){0,1}Summit( FT){0,1})(?!(.*Login)).*\r\nindex:=0",
      "ENUM_TYPE": null,
      "APPLICATION_ID": 234,
      "OBJECT_NAME_ID": 11892,
      "TYPE_NAME": "Pegwindow",
      "STEPS_ID": 288544,
      "COLUMN_ROW_SETTING": null,
      "COMMENTINFO": null,
      "IS_RUNNABLE": 0,
      "RUN_ORDER": 22,
      "VALUE_SETTING": null
    },
    {
      "dataForDataSets": [
        {
          "Data_Setting_Id": 280783,
          "DATASETVALUE": null,
          "DATA_SUMMARY_ID": 288014,
          "SKIP": 0,
          "STEPS_ID": 288544
        }
      ],
      "recordStatus": 0,
      "TEST_CASE_ID": 3245,
      "TEST_CASE_NAME": "Auto Rate Reset tc",
      "KEY_WORD_ID": 15,
      "KEY_WORD_NAME": "PegWindow",
      "OBJECT_HAPPY_NAME": "Summit Start",
      "OBJECT_ID": 46255,
      "OBJECT_TYPE": "Summit Start",
      "QUICK_ACCESS": "is owned window:=False\r\nis child window:=False\r\ntext:=((Misys|Finastra ){0,1}(FusionCapital|Fusion ){0,1}(Markets ){0,1}Summit( FT){0,1})(?!(.*Login)).*\r\nindex:=0",
      "ENUM_TYPE": null,
      "APPLICATION_ID": 293,
      "OBJECT_NAME_ID": 11892,
      "TYPE_NAME": "Pegwindow",
      "STEPS_ID": 288544,
      "COLUMN_ROW_SETTING": null,
      "COMMENTINFO": null,
      "IS_RUNNABLE": 0,
      "RUN_ORDER": 22,
      "VALUE_SETTING": null
    },
    {
      "dataForDataSets": [
        {
          "Data_Setting_Id": 280783,
          "DATASETVALUE": null,
          "DATA_SUMMARY_ID": 288014,
          "SKIP": 0,
          "STEPS_ID": 288544
        }
      ],
      "recordStatus": 0,
      "TEST_CASE_ID": 3245,
      "TEST_CASE_NAME": "Auto Rate Reset tc",
      "KEY_WORD_ID": 15,
      "KEY_WORD_NAME": "PegWindow",
      "OBJECT_HAPPY_NAME": "Summit Start",
      "OBJECT_ID": 3893,
      "OBJECT_TYPE": "Summit Start",
      "QUICK_ACCESS": "is owned window:=False\nis child window:=False\ntext:=((Misys ){0,1}(FusionCapital ){0,1}Summit( FT){0,1})(?!(.*Login)).*\r\nindex:=0",
      "ENUM_TYPE": null,
      "APPLICATION_ID": 2,
      "OBJECT_NAME_ID": 11892,
      "TYPE_NAME": "Pegwindow",
      "STEPS_ID": 288544,
      "COLUMN_ROW_SETTING": null,
      "COMMENTINFO": null,
      "IS_RUNNABLE": 0,
      "RUN_ORDER": 22,
      "VALUE_SETTING": null
    },
    {
      "dataForDataSets": [
        {
          "Data_Setting_Id": 280783,
          "DATASETVALUE": null,
          "DATA_SUMMARY_ID": 288014,
          "SKIP": 0,
          "STEPS_ID": 288544
        }
      ],
      "recordStatus": 0,
      "TEST_CASE_ID": 3245,
      "TEST_CASE_NAME": "Auto Rate Reset tc",
      "KEY_WORD_ID": 15,
      "KEY_WORD_NAME": "PegWindow",
      "OBJECT_HAPPY_NAME": "Summit Start",
      "OBJECT_ID": 61,
      "OBJECT_TYPE": "Summit Start",
      "QUICK_ACCESS": "is owned window:=False\r\nis child window:=False\r\ntext:=((Misys|Finastra ){0,1}(FusionCapital|Fusion ){0,1}(Markets ){0,1}Summit( FT){0,1})(?!(.*Login)).*\r\nindex:=0",
      "ENUM_TYPE": null,
      "APPLICATION_ID": 1,
      "OBJECT_NAME_ID": 11892,
      "TYPE_NAME": "Pegwindow",
      "STEPS_ID": 288544,
      "COLUMN_ROW_SETTING": null,
      "COMMENTINFO": null,
      "IS_RUNNABLE": 0,
      "RUN_ORDER": 22,
      "VALUE_SETTING": null
    },
    {
      "dataForDataSets": [
        {
          "Data_Setting_Id": 280783,
          "DATASETVALUE": null,
          "DATA_SUMMARY_ID": 288014,
          "SKIP": 0,
          "STEPS_ID": 288544
        }
      ],
      "recordStatus": 0,
      "TEST_CASE_ID": 3245,
      "TEST_CASE_NAME": "Auto Rate Reset tc",
      "KEY_WORD_ID": 15,
      "KEY_WORD_NAME": "PegWindow",
      "OBJECT_HAPPY_NAME": "Summit Start",
      "OBJECT_ID": 16827,
      "OBJECT_TYPE": "Summit Start",
      "QUICK_ACCESS": "is owned window:=False\nis child window:=False\ntext:=((Misys ){0,1}(FusionCapital ){0,1}Summit( FT){0,1})(?!(.*Login)).*\r\nindex:=0",
      "ENUM_TYPE": null,
      "APPLICATION_ID": 173,
      "OBJECT_NAME_ID": 11892,
      "TYPE_NAME": "Pegwindow",
      "STEPS_ID": 288544,
      "COLUMN_ROW_SETTING": null,
      "COMMENTINFO": null,
      "IS_RUNNABLE": 0,
      "RUN_ORDER": 22,
      "VALUE_SETTING": null
    },
    {
      "dataForDataSets": [
        {
          "Data_Setting_Id": 280783,
          "DATASETVALUE": null,
          "DATA_SUMMARY_ID": 288014,
          "SKIP": 0,
          "STEPS_ID": 288544
        }
      ],
      "recordStatus": 0,
      "TEST_CASE_ID": 3245,
      "TEST_CASE_NAME": "Auto Rate Reset tc",
      "KEY_WORD_ID": 15,
      "KEY_WORD_NAME": "PegWindow",
      "OBJECT_HAPPY_NAME": "Summit Start",
      "OBJECT_ID": 20724,
      "OBJECT_TYPE": "Summit Start",
      "QUICK_ACCESS": "is owned window:=False\nis child window:=False\ntext:=(Misys ){0,1}Summit FT.*",
      "ENUM_TYPE": null,
      "APPLICATION_ID": 133,
      "OBJECT_NAME_ID": 11892,
      "TYPE_NAME": "Pegwindow",
      "STEPS_ID": 288544,
      "COLUMN_ROW_SETTING": null,
      "COMMENTINFO": null,
      "IS_RUNNABLE": 0,
      "RUN_ORDER": 22,
      "VALUE_SETTING": null
    },
    {
      "dataForDataSets": [
        {
          "Data_Setting_Id": 280783,
          "DATASETVALUE": null,
          "DATA_SUMMARY_ID": 288014,
          "SKIP": 0,
          "STEPS_ID": 288544
        }
      ],
      "recordStatus": 0,
      "TEST_CASE_ID": 3245,
      "TEST_CASE_NAME": "Auto Rate Reset tc",
      "KEY_WORD_ID": 15,
      "KEY_WORD_NAME": "PegWindow",
      "OBJECT_HAPPY_NAME": "Summit Start",
      "OBJECT_ID": 32573,
      "OBJECT_TYPE": "Summit Start",
      "QUICK_ACCESS": "is owned window:=False\nis child window:=False\ntext:=((Misys ){0,1}(FusionCapital ){0,1}Summit( FT){0,1})(?!(.*Login)).*\r\nindex:=0",
      "ENUM_TYPE": null,
      "APPLICATION_ID": 213,
      "OBJECT_NAME_ID": 11892,
      "TYPE_NAME": "Pegwindow",
      "STEPS_ID": 288544,
      "COLUMN_ROW_SETTING": null,
      "COMMENTINFO": null,
      "IS_RUNNABLE": 0,
      "RUN_ORDER": 22,
      "VALUE_SETTING": null
    },
    {
      "dataForDataSets": [
        {
          "Data_Setting_Id": 280785,
          "DATASETVALUE": "Save Reset Rate.*",
          "DATA_SUMMARY_ID": 288014,
          "SKIP": 0,
          "STEPS_ID": 288499
        }
      ],
      "recordStatus": 0,
      "TEST_CASE_ID": 3245,
      "TEST_CASE_NAME": "Auto Rate Reset tc",
      "KEY_WORD_ID": 5,
      "KEY_WORD_NAME": "ClickMenuIcon",
      "OBJECT_HAPPY_NAME": null,
      "OBJECT_ID": -1,
      "OBJECT_TYPE": null,
      "QUICK_ACCESS": null,
      "ENUM_TYPE": null,
      "APPLICATION_ID": -1,
      "OBJECT_NAME_ID": -1,
      "TYPE_NAME": " ",
      "STEPS_ID": 288499,
      "COLUMN_ROW_SETTING": "Save Reset Rate",
      "COMMENTINFO": null,
      "IS_RUNNABLE": 0,
      "RUN_ORDER": 23,
      "VALUE_SETTING": null
    },
    {
      "dataForDataSets": [
        {
          "Data_Setting_Id": 280784,
          "DATASETVALUE": null,
          "DATA_SUMMARY_ID": 288014,
          "SKIP": 0,
          "STEPS_ID": 288545
        }
      ],
      "recordStatus": 0,
      "TEST_CASE_ID": 3245,
      "TEST_CASE_NAME": "Auto Rate Reset tc",
      "KEY_WORD_ID": 15,
      "KEY_WORD_NAME": "PegWindow",
      "OBJECT_HAPPY_NAME": "AUTO_ RATE_RESET",
      "OBJECT_ID": 27513,
      "OBJECT_TYPE": "AUTO_ RATE_RESET",
      "QUICK_ACCESS": "is owned window:=False\nis child window:=False\nText:=^((Misys|Finastra ){0,1}(FusionCapital|Fusion ){0,1}(Markets ){0,1}Summit( FT){0,1})(?!(.*Login)).*",
      "ENUM_TYPE": null,
      "APPLICATION_ID": 1,
      "OBJECT_NAME_ID": 27420,
      "TYPE_NAME": "Pegwindow",
      "STEPS_ID": 288545,
      "COLUMN_ROW_SETTING": null,
      "COMMENTINFO": null,
      "IS_RUNNABLE": 0,
      "RUN_ORDER": 24,
      "VALUE_SETTING": null
    },
    {
      "dataForDataSets": [
        {
          "Data_Setting_Id": 280784,
          "DATASETVALUE": null,
          "DATA_SUMMARY_ID": 288014,
          "SKIP": 0,
          "STEPS_ID": 288545
        }
      ],
      "recordStatus": 0,
      "TEST_CASE_ID": 3245,
      "TEST_CASE_NAME": "Auto Rate Reset tc",
      "KEY_WORD_ID": 15,
      "KEY_WORD_NAME": "PegWindow",
      "OBJECT_HAPPY_NAME": "AUTO_ RATE_RESET",
      "OBJECT_ID": 41245,
      "OBJECT_TYPE": "AUTO_ RATE_RESET",
      "QUICK_ACCESS": "is owned window:=False\nis child window:=False\nText:=^((Misys|Finastra ){0,1}(FusionCapital|Fusion ){0,1}(Markets ){0,1}Summit( FT){0,1})(?!(.*Login)).*",
      "ENUM_TYPE": null,
      "APPLICATION_ID": 234,
      "OBJECT_NAME_ID": 27420,
      "TYPE_NAME": "Pegwindow",
      "STEPS_ID": 288545,
      "COLUMN_ROW_SETTING": null,
      "COMMENTINFO": null,
      "IS_RUNNABLE": 0,
      "RUN_ORDER": 24,
      "VALUE_SETTING": null
    },
    {
      "dataForDataSets": [
        {
          "Data_Setting_Id": 280784,
          "DATASETVALUE": null,
          "DATA_SUMMARY_ID": 288014,
          "SKIP": 0,
          "STEPS_ID": 288545
        }
      ],
      "recordStatus": 0,
      "TEST_CASE_ID": 3245,
      "TEST_CASE_NAME": "Auto Rate Reset tc",
      "KEY_WORD_ID": 15,
      "KEY_WORD_NAME": "PegWindow",
      "OBJECT_HAPPY_NAME": "AUTO_ RATE_RESET",
      "OBJECT_ID": 48643,
      "OBJECT_TYPE": "AUTO_ RATE_RESET",
      "QUICK_ACCESS": "is owned window:=False\nis child window:=False\nText:=^((Misys|Finastra ){0,1}(FusionCapital|Fusion ){0,1}(Markets ){0,1}Summit( FT){0,1})(?!(.*Login)).*",
      "ENUM_TYPE": null,
      "APPLICATION_ID": 293,
      "OBJECT_NAME_ID": 27420,
      "TYPE_NAME": "Pegwindow",
      "STEPS_ID": 288545,
      "COLUMN_ROW_SETTING": null,
      "COMMENTINFO": null,
      "IS_RUNNABLE": 0,
      "RUN_ORDER": 24,
      "VALUE_SETTING": null
    },
    {
      "dataForDataSets": [
        {
          "Data_Setting_Id": 280679,
          "DATASETVALUE": null,
          "DATA_SUMMARY_ID": 288014,
          "SKIP": 0,
          "STEPS_ID": 288160
        }
      ],
      "recordStatus": 0,
      "TEST_CASE_ID": 3245,
      "TEST_CASE_NAME": "Auto Rate Reset tc",
      "KEY_WORD_ID": 4,
      "KEY_WORD_NAME": "ClickButton",
      "OBJECT_HAPPY_NAME": "AUTO_ RATE_RESET_SAVE_EXIT",
      "OBJECT_ID": 27511,
      "OBJECT_TYPE": "AUTO_ RATE_RESET",
      "QUICK_ACCESS": "swfname:=_saveExitButton",
      "ENUM_TYPE": null,
      "APPLICATION_ID": 1,
      "OBJECT_NAME_ID": 27452,
      "TYPE_NAME": "SwfButton",
      "STEPS_ID": 288160,
      "COLUMN_ROW_SETTING": null,
      "COMMENTINFO": null,
      "IS_RUNNABLE": 0,
      "RUN_ORDER": 25,
      "VALUE_SETTING": null
    },
    {
      "dataForDataSets": [
        {
          "Data_Setting_Id": 280679,
          "DATASETVALUE": null,
          "DATA_SUMMARY_ID": 288014,
          "SKIP": 0,
          "STEPS_ID": 288160
        }
      ],
      "recordStatus": 0,
      "TEST_CASE_ID": 3245,
      "TEST_CASE_NAME": "Auto Rate Reset tc",
      "KEY_WORD_ID": 4,
      "KEY_WORD_NAME": "ClickButton",
      "OBJECT_HAPPY_NAME": "AUTO_ RATE_RESET_SAVE_EXIT",
      "OBJECT_ID": 41243,
      "OBJECT_TYPE": "AUTO_ RATE_RESET",
      "QUICK_ACCESS": "swfname:=_saveExitButton",
      "ENUM_TYPE": null,
      "APPLICATION_ID": 234,
      "OBJECT_NAME_ID": 27452,
      "TYPE_NAME": "SwfButton",
      "STEPS_ID": 288160,
      "COLUMN_ROW_SETTING": null,
      "COMMENTINFO": null,
      "IS_RUNNABLE": 0,
      "RUN_ORDER": 25,
      "VALUE_SETTING": null
    },
    {
      "dataForDataSets": [
        {
          "Data_Setting_Id": 280679,
          "DATASETVALUE": null,
          "DATA_SUMMARY_ID": 288014,
          "SKIP": 0,
          "STEPS_ID": 288160
        }
      ],
      "recordStatus": 0,
      "TEST_CASE_ID": 3245,
      "TEST_CASE_NAME": "Auto Rate Reset tc",
      "KEY_WORD_ID": 4,
      "KEY_WORD_NAME": "ClickButton",
      "OBJECT_HAPPY_NAME": "AUTO_ RATE_RESET_SAVE_EXIT",
      "OBJECT_ID": 48641,
      "OBJECT_TYPE": "AUTO_ RATE_RESET",
      "QUICK_ACCESS": "swfname:=_saveExitButton",
      "ENUM_TYPE": null,
      "APPLICATION_ID": 293,
      "OBJECT_NAME_ID": 27452,
      "TYPE_NAME": "SwfButton",
      "STEPS_ID": 288160,
      "COLUMN_ROW_SETTING": null,
      "COMMENTINFO": null,
      "IS_RUNNABLE": 0,
      "RUN_ORDER": 25,
      "VALUE_SETTING": null
    },
    {
      "dataForDataSets": [
        {
          "Data_Setting_Id": 280772,
          "DATASETVALUE": "10",
          "DATA_SUMMARY_ID": 288014,
          "SKIP": 0,
          "STEPS_ID": 288502
        }
      ],
      "recordStatus": 0,
      "TEST_CASE_ID": 3245,
      "TEST_CASE_NAME": "Auto Rate Reset tc",
      "KEY_WORD_ID": 37,
      "KEY_WORD_NAME": "WaitForSeconds",
      "OBJECT_HAPPY_NAME": null,
      "OBJECT_ID": -1,
      "OBJECT_TYPE": null,
      "QUICK_ACCESS": null,
      "ENUM_TYPE": null,
      "APPLICATION_ID": -1,
      "OBJECT_NAME_ID": -1,
      "TYPE_NAME": " ",
      "STEPS_ID": 288502,
      "COLUMN_ROW_SETTING": null,
      "COMMENTINFO": null,
      "IS_RUNNABLE": 0,
      "RUN_ORDER": 26,
      "VALUE_SETTING": null
    },
    {
      "dataForDataSets": [
        {
          "Data_Setting_Id": 280767,
          "DATASETVALUE": null,
          "DATA_SUMMARY_ID": 288014,
          "SKIP": 0,
          "STEPS_ID": 288497
        }
      ],
      "recordStatus": 0,
      "TEST_CASE_ID": 3245,
      "TEST_CASE_NAME": "Auto Rate Reset tc",
      "KEY_WORD_ID": 78,
      "KEY_WORD_NAME": "SnapShot",
      "OBJECT_HAPPY_NAME": "AUTO_RATE_RESET_PANEL",
      "OBJECT_ID": 27639,
      "OBJECT_TYPE": "AUTO_ RATE_RESET",
      "QUICK_ACCESS": "swfname:=AutoRateResetView",
      "ENUM_TYPE": null,
      "APPLICATION_ID": 1,
      "OBJECT_NAME_ID": 27638,
      "TYPE_NAME": "SwfWindow",
      "STEPS_ID": 288497,
      "COLUMN_ROW_SETTING": null,
      "COMMENTINFO": null,
      "IS_RUNNABLE": 0,
      "RUN_ORDER": 27,
      "VALUE_SETTING": null
    },
    {
      "dataForDataSets": [
        {
          "Data_Setting_Id": 280767,
          "DATASETVALUE": null,
          "DATA_SUMMARY_ID": 288014,
          "SKIP": 0,
          "STEPS_ID": 288497
        }
      ],
      "recordStatus": 0,
      "TEST_CASE_ID": 3245,
      "TEST_CASE_NAME": "Auto Rate Reset tc",
      "KEY_WORD_ID": 78,
      "KEY_WORD_NAME": "SnapShot",
      "OBJECT_HAPPY_NAME": "AUTO_RATE_RESET_PANEL",
      "OBJECT_ID": 41272,
      "OBJECT_TYPE": "AUTO_ RATE_RESET",
      "QUICK_ACCESS": "swfname:=AutoRateResetView",
      "ENUM_TYPE": null,
      "APPLICATION_ID": 234,
      "OBJECT_NAME_ID": 27638,
      "TYPE_NAME": "SwfWindow",
      "STEPS_ID": 288497,
      "COLUMN_ROW_SETTING": null,
      "COMMENTINFO": null,
      "IS_RUNNABLE": 0,
      "RUN_ORDER": 27,
      "VALUE_SETTING": null
    },
    {
      "dataForDataSets": [
        {
          "Data_Setting_Id": 280767,
          "DATASETVALUE": null,
          "DATA_SUMMARY_ID": 288014,
          "SKIP": 0,
          "STEPS_ID": 288497
        }
      ],
      "recordStatus": 0,
      "TEST_CASE_ID": 3245,
      "TEST_CASE_NAME": "Auto Rate Reset tc",
      "KEY_WORD_ID": 78,
      "KEY_WORD_NAME": "SnapShot",
      "OBJECT_HAPPY_NAME": "AUTO_RATE_RESET_PANEL",
      "OBJECT_ID": 48670,
      "OBJECT_TYPE": "AUTO_ RATE_RESET",
      "QUICK_ACCESS": "swfname:=AutoRateResetView",
      "ENUM_TYPE": null,
      "APPLICATION_ID": 293,
      "OBJECT_NAME_ID": 27638,
      "TYPE_NAME": "SwfWindow",
      "STEPS_ID": 288497,
      "COLUMN_ROW_SETTING": null,
      "COMMENTINFO": null,
      "IS_RUNNABLE": 0,
      "RUN_ORDER": 27,
      "VALUE_SETTING": null
    },
    {
      "dataForDataSets": [
        {
          "Data_Setting_Id": 280771,
          "DATASETVALUE": null,
          "DATA_SUMMARY_ID": 288014,
          "SKIP": 0,
          "STEPS_ID": 288501
        }
      ],
      "recordStatus": 0,
      "TEST_CASE_ID": 3245,
      "TEST_CASE_NAME": "Auto Rate Reset tc",
      "KEY_WORD_ID": 15,
      "KEY_WORD_NAME": "PegWindow",
      "OBJECT_HAPPY_NAME": "Summit Start",
      "OBJECT_ID": 38857,
      "OBJECT_TYPE": "Summit Start",
      "QUICK_ACCESS": "is owned window:=False\r\nis child window:=False\r\ntext:=((Misys|Finastra ){0,1}(FusionCapital|Fusion ){0,1}(Markets ){0,1}Summit( FT){0,1})(?!(.*Login)).*\r\nindex:=0",
      "ENUM_TYPE": null,
      "APPLICATION_ID": 234,
      "OBJECT_NAME_ID": 11892,
      "TYPE_NAME": "Pegwindow",
      "STEPS_ID": 288501,
      "COLUMN_ROW_SETTING": null,
      "COMMENTINFO": null,
      "IS_RUNNABLE": 0,
      "RUN_ORDER": 28,
      "VALUE_SETTING": null
    },
    {
      "dataForDataSets": [
        {
          "Data_Setting_Id": 280771,
          "DATASETVALUE": null,
          "DATA_SUMMARY_ID": 288014,
          "SKIP": 0,
          "STEPS_ID": 288501
        }
      ],
      "recordStatus": 0,
      "TEST_CASE_ID": 3245,
      "TEST_CASE_NAME": "Auto Rate Reset tc",
      "KEY_WORD_ID": 15,
      "KEY_WORD_NAME": "PegWindow",
      "OBJECT_HAPPY_NAME": "Summit Start",
      "OBJECT_ID": 46255,
      "OBJECT_TYPE": "Summit Start",
      "QUICK_ACCESS": "is owned window:=False\r\nis child window:=False\r\ntext:=((Misys|Finastra ){0,1}(FusionCapital|Fusion ){0,1}(Markets ){0,1}Summit( FT){0,1})(?!(.*Login)).*\r\nindex:=0",
      "ENUM_TYPE": null,
      "APPLICATION_ID": 293,
      "OBJECT_NAME_ID": 11892,
      "TYPE_NAME": "Pegwindow",
      "STEPS_ID": 288501,
      "COLUMN_ROW_SETTING": null,
      "COMMENTINFO": null,
      "IS_RUNNABLE": 0,
      "RUN_ORDER": 28,
      "VALUE_SETTING": null
    },
    {
      "dataForDataSets": [
        {
          "Data_Setting_Id": 280771,
          "DATASETVALUE": null,
          "DATA_SUMMARY_ID": 288014,
          "SKIP": 0,
          "STEPS_ID": 288501
        }
      ],
      "recordStatus": 0,
      "TEST_CASE_ID": 3245,
      "TEST_CASE_NAME": "Auto Rate Reset tc",
      "KEY_WORD_ID": 15,
      "KEY_WORD_NAME": "PegWindow",
      "OBJECT_HAPPY_NAME": "Summit Start",
      "OBJECT_ID": 3893,
      "OBJECT_TYPE": "Summit Start",
      "QUICK_ACCESS": "is owned window:=False\nis child window:=False\ntext:=((Misys ){0,1}(FusionCapital ){0,1}Summit( FT){0,1})(?!(.*Login)).*\r\nindex:=0",
      "ENUM_TYPE": null,
      "APPLICATION_ID": 2,
      "OBJECT_NAME_ID": 11892,
      "TYPE_NAME": "Pegwindow",
      "STEPS_ID": 288501,
      "COLUMN_ROW_SETTING": null,
      "COMMENTINFO": null,
      "IS_RUNNABLE": 0,
      "RUN_ORDER": 28,
      "VALUE_SETTING": null
    },
    {
      "dataForDataSets": [
        {
          "Data_Setting_Id": 280771,
          "DATASETVALUE": null,
          "DATA_SUMMARY_ID": 288014,
          "SKIP": 0,
          "STEPS_ID": 288501
        }
      ],
      "recordStatus": 0,
      "TEST_CASE_ID": 3245,
      "TEST_CASE_NAME": "Auto Rate Reset tc",
      "KEY_WORD_ID": 15,
      "KEY_WORD_NAME": "PegWindow",
      "OBJECT_HAPPY_NAME": "Summit Start",
      "OBJECT_ID": 61,
      "OBJECT_TYPE": "Summit Start",
      "QUICK_ACCESS": "is owned window:=False\r\nis child window:=False\r\ntext:=((Misys|Finastra ){0,1}(FusionCapital|Fusion ){0,1}(Markets ){0,1}Summit( FT){0,1})(?!(.*Login)).*\r\nindex:=0",
      "ENUM_TYPE": null,
      "APPLICATION_ID": 1,
      "OBJECT_NAME_ID": 11892,
      "TYPE_NAME": "Pegwindow",
      "STEPS_ID": 288501,
      "COLUMN_ROW_SETTING": null,
      "COMMENTINFO": null,
      "IS_RUNNABLE": 0,
      "RUN_ORDER": 28,
      "VALUE_SETTING": null
    },
    {
      "dataForDataSets": [
        {
          "Data_Setting_Id": 280771,
          "DATASETVALUE": null,
          "DATA_SUMMARY_ID": 288014,
          "SKIP": 0,
          "STEPS_ID": 288501
        }
      ],
      "recordStatus": 0,
      "TEST_CASE_ID": 3245,
      "TEST_CASE_NAME": "Auto Rate Reset tc",
      "KEY_WORD_ID": 15,
      "KEY_WORD_NAME": "PegWindow",
      "OBJECT_HAPPY_NAME": "Summit Start",
      "OBJECT_ID": 16827,
      "OBJECT_TYPE": "Summit Start",
      "QUICK_ACCESS": "is owned window:=False\nis child window:=False\ntext:=((Misys ){0,1}(FusionCapital ){0,1}Summit( FT){0,1})(?!(.*Login)).*\r\nindex:=0",
      "ENUM_TYPE": null,
      "APPLICATION_ID": 173,
      "OBJECT_NAME_ID": 11892,
      "TYPE_NAME": "Pegwindow",
      "STEPS_ID": 288501,
      "COLUMN_ROW_SETTING": null,
      "COMMENTINFO": null,
      "IS_RUNNABLE": 0,
      "RUN_ORDER": 28,
      "VALUE_SETTING": null
    },
    {
      "dataForDataSets": [
        {
          "Data_Setting_Id": 280771,
          "DATASETVALUE": null,
          "DATA_SUMMARY_ID": 288014,
          "SKIP": 0,
          "STEPS_ID": 288501
        }
      ],
      "recordStatus": 0,
      "TEST_CASE_ID": 3245,
      "TEST_CASE_NAME": "Auto Rate Reset tc",
      "KEY_WORD_ID": 15,
      "KEY_WORD_NAME": "PegWindow",
      "OBJECT_HAPPY_NAME": "Summit Start",
      "OBJECT_ID": 20724,
      "OBJECT_TYPE": "Summit Start",
      "QUICK_ACCESS": "is owned window:=False\nis child window:=False\ntext:=(Misys ){0,1}Summit FT.*",
      "ENUM_TYPE": null,
      "APPLICATION_ID": 133,
      "OBJECT_NAME_ID": 11892,
      "TYPE_NAME": "Pegwindow",
      "STEPS_ID": 288501,
      "COLUMN_ROW_SETTING": null,
      "COMMENTINFO": null,
      "IS_RUNNABLE": 0,
      "RUN_ORDER": 28,
      "VALUE_SETTING": null
    },
    {
      "dataForDataSets": [
        {
          "Data_Setting_Id": 280771,
          "DATASETVALUE": null,
          "DATA_SUMMARY_ID": 288014,
          "SKIP": 0,
          "STEPS_ID": 288501
        }
      ],
      "recordStatus": 0,
      "TEST_CASE_ID": 3245,
      "TEST_CASE_NAME": "Auto Rate Reset tc",
      "KEY_WORD_ID": 15,
      "KEY_WORD_NAME": "PegWindow",
      "OBJECT_HAPPY_NAME": "Summit Start",
      "OBJECT_ID": 32573,
      "OBJECT_TYPE": "Summit Start",
      "QUICK_ACCESS": "is owned window:=False\nis child window:=False\ntext:=((Misys ){0,1}(FusionCapital ){0,1}Summit( FT){0,1})(?!(.*Login)).*\r\nindex:=0",
      "ENUM_TYPE": null,
      "APPLICATION_ID": 213,
      "OBJECT_NAME_ID": 11892,
      "TYPE_NAME": "Pegwindow",
      "STEPS_ID": 288501,
      "COLUMN_ROW_SETTING": null,
      "COMMENTINFO": null,
      "IS_RUNNABLE": 0,
      "RUN_ORDER": 28,
      "VALUE_SETTING": null
    },
    {
      "dataForDataSets": [
        {
          "Data_Setting_Id": 280768,
          "DATASETVALUE": null,
          "DATA_SUMMARY_ID": 288014,
          "SKIP": 0,
          "STEPS_ID": 288498
        }
      ],
      "recordStatus": 0,
      "TEST_CASE_ID": 3245,
      "TEST_CASE_NAME": "Auto Rate Reset tc",
      "KEY_WORD_ID": 4,
      "KEY_WORD_NAME": "ClickButton",
      "OBJECT_HAPPY_NAME": "CLOSE_BUTTON",
      "OBJECT_ID": 38858,
      "OBJECT_TYPE": "Summit Start",
      "QUICK_ACCESS": "swfname:=_closeButton\nswftypename:=Summit.Framework.DesktopContent.ImageButton\nindex:=0",
      "ENUM_TYPE": null,
      "APPLICATION_ID": 234,
      "OBJECT_NAME_ID": 13105,
      "TYPE_NAME": "SwfButton",
      "STEPS_ID": 288498,
      "COLUMN_ROW_SETTING": null,
      "COMMENTINFO": null,
      "IS_RUNNABLE": 0,
      "RUN_ORDER": 29,
      "VALUE_SETTING": null
    },
    {
      "dataForDataSets": [
        {
          "Data_Setting_Id": 280768,
          "DATASETVALUE": null,
          "DATA_SUMMARY_ID": 288014,
          "SKIP": 0,
          "STEPS_ID": 288498
        }
      ],
      "recordStatus": 0,
      "TEST_CASE_ID": 3245,
      "TEST_CASE_NAME": "Auto Rate Reset tc",
      "KEY_WORD_ID": 4,
      "KEY_WORD_NAME": "ClickButton",
      "OBJECT_HAPPY_NAME": "CLOSE_BUTTON",
      "OBJECT_ID": 46256,
      "OBJECT_TYPE": "Summit Start",
      "QUICK_ACCESS": "swfname:=_closeButton\nswftypename:=Summit.Framework.DesktopContent.ImageButton\nindex:=0",
      "ENUM_TYPE": null,
      "APPLICATION_ID": 293,
      "OBJECT_NAME_ID": 13105,
      "TYPE_NAME": "SwfButton",
      "STEPS_ID": 288498,
      "COLUMN_ROW_SETTING": null,
      "COMMENTINFO": null,
      "IS_RUNNABLE": 0,
      "RUN_ORDER": 29,
      "VALUE_SETTING": null
    },
    {
      "dataForDataSets": [
        {
          "Data_Setting_Id": 280768,
          "DATASETVALUE": null,
          "DATA_SUMMARY_ID": 288014,
          "SKIP": 0,
          "STEPS_ID": 288498
        }
      ],
      "recordStatus": 0,
      "TEST_CASE_ID": 3245,
      "TEST_CASE_NAME": "Auto Rate Reset tc",
      "KEY_WORD_ID": 4,
      "KEY_WORD_NAME": "ClickButton",
      "OBJECT_HAPPY_NAME": "CLOSE_BUTTON",
      "OBJECT_ID": 10575,
      "OBJECT_TYPE": "Summit Start",
      "QUICK_ACCESS": "swfname:=_closeButton\r\nswftypename:=Summit.Framework.DesktopContent.ImageButton",
      "ENUM_TYPE": null,
      "APPLICATION_ID": 2,
      "OBJECT_NAME_ID": 13105,
      "TYPE_NAME": "SwfButton",
      "STEPS_ID": 288498,
      "COLUMN_ROW_SETTING": null,
      "COMMENTINFO": null,
      "IS_RUNNABLE": 0,
      "RUN_ORDER": 29,
      "VALUE_SETTING": null
    },
    {
      "dataForDataSets": [
        {
          "Data_Setting_Id": 280768,
          "DATASETVALUE": null,
          "DATA_SUMMARY_ID": 288014,
          "SKIP": 0,
          "STEPS_ID": 288498
        }
      ],
      "recordStatus": 0,
      "TEST_CASE_ID": 3245,
      "TEST_CASE_NAME": "Auto Rate Reset tc",
      "KEY_WORD_ID": 4,
      "KEY_WORD_NAME": "ClickButton",
      "OBJECT_HAPPY_NAME": "CLOSE_BUTTON",
      "OBJECT_ID": 9052,
      "OBJECT_TYPE": "Summit Start",
      "QUICK_ACCESS": "swfname:=_closeButton\nswftypename:=Summit.Framework.DesktopContent.ImageButton\nindex:=0",
      "ENUM_TYPE": null,
      "APPLICATION_ID": 1,
      "OBJECT_NAME_ID": 13105,
      "TYPE_NAME": "SwfButton",
      "STEPS_ID": 288498,
      "COLUMN_ROW_SETTING": null,
      "COMMENTINFO": null,
      "IS_RUNNABLE": 0,
      "RUN_ORDER": 29,
      "VALUE_SETTING": null
    },
    {
      "dataForDataSets": [
        {
          "Data_Setting_Id": 280768,
          "DATASETVALUE": null,
          "DATA_SUMMARY_ID": 288014,
          "SKIP": 0,
          "STEPS_ID": 288498
        }
      ],
      "recordStatus": 0,
      "TEST_CASE_ID": 3245,
      "TEST_CASE_NAME": "Auto Rate Reset tc",
      "KEY_WORD_ID": 4,
      "KEY_WORD_NAME": "ClickButton",
      "OBJECT_HAPPY_NAME": "CLOSE_BUTTON",
      "OBJECT_ID": 16828,
      "OBJECT_TYPE": "Summit Start",
      "QUICK_ACCESS": "swfname:=_closeButton",
      "ENUM_TYPE": null,
      "APPLICATION_ID": 173,
      "OBJECT_NAME_ID": 13105,
      "TYPE_NAME": "SwfButton",
      "STEPS_ID": 288498,
      "COLUMN_ROW_SETTING": null,
      "COMMENTINFO": null,
      "IS_RUNNABLE": 0,
      "RUN_ORDER": 29,
      "VALUE_SETTING": null
    },
    {
      "dataForDataSets": [
        {
          "Data_Setting_Id": 280768,
          "DATASETVALUE": null,
          "DATA_SUMMARY_ID": 288014,
          "SKIP": 0,
          "STEPS_ID": 288498
        }
      ],
      "recordStatus": 0,
      "TEST_CASE_ID": 3245,
      "TEST_CASE_NAME": "Auto Rate Reset tc",
      "KEY_WORD_ID": 4,
      "KEY_WORD_NAME": "ClickButton",
      "OBJECT_HAPPY_NAME": "CLOSE_BUTTON",
      "OBJECT_ID": 32574,
      "OBJECT_TYPE": "Summit Start",
      "QUICK_ACCESS": "swfname:=_closeButton\r\nswftypename:=Summit.Framework.DesktopContent.ImageButton",
      "ENUM_TYPE": null,
      "APPLICATION_ID": 213,
      "OBJECT_NAME_ID": 13105,
      "TYPE_NAME": "SwfButton",
      "STEPS_ID": 288498,
      "COLUMN_ROW_SETTING": null,
      "COMMENTINFO": null,
      "IS_RUNNABLE": 0,
      "RUN_ORDER": 29,
      "VALUE_SETTING": null
    },
    {
      "dataForDataSets": [
        {
          "Data_Setting_Id": 280770,
          "DATASETVALUE": null,
          "DATA_SUMMARY_ID": 288014,
          "SKIP": 0,
          "STEPS_ID": 288500
        }
      ],
      "recordStatus": 0,
      "TEST_CASE_ID": 3245,
      "TEST_CASE_NAME": "Auto Rate Reset tc",
      "KEY_WORD_ID": 38,
      "KEY_WORD_NAME": "Dismiss",
      "OBJECT_HAPPY_NAME": null,
      "OBJECT_ID": -1,
      "OBJECT_TYPE": null,
      "QUICK_ACCESS": null,
      "ENUM_TYPE": null,
      "APPLICATION_ID": -1,
      "OBJECT_NAME_ID": -1,
      "TYPE_NAME": " ",
      "STEPS_ID": 288500,
      "COLUMN_ROW_SETTING": "5",
      "COMMENTINFO": null,
      "IS_RUNNABLE": 0,
      "RUN_ORDER": 30,
      "VALUE_SETTING": null
    }
  ]
}