{
  "currentSyncroStatus": 0,
  "assignedApplications": [
    193,
    194,
    -1
  ],
  "assignedTestSuiteIDs": [
    1404
  ],
  "version": null,
  "assignedDataSets": [
    {
      "recordStatus": 0,
      "DATA_SUMMARY_ID": 436382,
      "ALIAS_NAME": "LAM_20",
      "DESCRIPTION_INFO": "FUT_01_VER"
    },
    {
      "recordStatus": 0,
      "DATA_SUMMARY_ID": 436377,
      "ALIAS_NAME": "FUT_01_VER",
      "DESCRIPTION_INFO": "FUT_01_VER"
    },
    {
      "recordStatus": 0,
      "DATA_SUMMARY_ID": 436378,
      "ALIAS_NAME": "LAM_21_b",
      "DESCRIPTION_INFO": "FUT_01_VER"
    }
  ],
  "allSteps": [
    {
      "dataForDataSets": [
        {
          "Data_Setting_Id": 291829,
          "DATASETVALUE": null,
          "DATA_SUMMARY_ID": 436377,
          "SKIP": 0,
          "STEPS_ID": 436443
        },
        {
          "Data_Setting_Id": 291831,
          "DATASETVALUE": null,
          "DATA_SUMMARY_ID": 436382,
          "SKIP": 0,
          "STEPS_ID": 436443
        },
        {
          "Data_Setting_Id": 291830,
          "DATASETVALUE": null,
          "DATA_SUMMARY_ID": 436378,
          "SKIP": 0,
          "STEPS_ID": 436443
        }
      ],
      "recordStatus": 0,
      "TEST_CASE_ID": 3086,
      "TEST_CASE_NAME": "Futures Trd Action Util",
      "KEY_WORD_ID": 15,
      "KEY_WORD_NAME": "PegWindow",
      "OBJECT_HAPPY_NAME": "Summit Start",
      "OBJECT_ID": 32286,
      "OBJECT_TYPE": "Summit Start",
      "QUICK_ACCESS": "swfname:=Desktop|Page\nText:=^((Misys|Finastra ){0,1}(FusionCapital|Fusion ){0,1}(Markets ){0,1}Summit( FT){0,1})(?!(.*Login)).*\nswftypename:=Summit\\.Framework\\.Desktop\\.(Desktop|Page){1}\nindex:=0",
      "ENUM_TYPE": null,
      "APPLICATION_ID": 193,
      "OBJECT_NAME_ID": 24912,
      "TYPE_NAME": "Pegwindow",
      "STEPS_ID": 436443,
      "COLUMN_ROW_SETTING": null,
      "COMMENTINFO": null,
      "IS_RUNNABLE": null,
      "RUN_ORDER": 1,
      "VALUE_SETTING": null
    },
    {
      "dataForDataSets": [
        {
          "Data_Setting_Id": 291829,
          "DATASETVALUE": null,
          "DATA_SUMMARY_ID": 436377,
          "SKIP": 0,
          "STEPS_ID": 436443
        },
        {
          "Data_Setting_Id": 291831,
          "DATASETVALUE": null,
          "DATA_SUMMARY_ID": 436382,
          "SKIP": 0,
          "STEPS_ID": 436443
        },
        {
          "Data_Setting_Id": 291830,
          "DATASETVALUE": null,
          "DATA_SUMMARY_ID": 436378,
          "SKIP": 0,
          "STEPS_ID": 436443
        }
      ],
      "recordStatus": 0,
      "TEST_CASE_ID": 3086,
      "TEST_CASE_NAME": "Futures Trd Action Util",
      "KEY_WORD_ID": 15,
      "KEY_WORD_NAME": "PegWindow",
      "OBJECT_HAPPY_NAME": "Summit Start",
      "OBJECT_ID": 40604,
      "OBJECT_TYPE": "Summit Start",
      "QUICK_ACCESS": "swfname:=Desktop|Page\nText:=^((Misys|Finastra ){0,1}(FusionCapital|Fusion ){0,1}(Markets ){0,1}Summit( FT){0,1})(?!(.*Login)).*\nswftypename:=Summit\\.Framework\\.Desktop\\.(Desktop|Page){1}\nindex:=0",
      "ENUM_TYPE": null,
      "APPLICATION_ID": 194,
      "OBJECT_NAME_ID": 24912,
      "TYPE_NAME": "Pegwindow",
      "STEPS_ID": 436443,
      "COLUMN_ROW_SETTING": null,
      "COMMENTINFO": null,
      "IS_RUNNABLE": null,
      "RUN_ORDER": 1,
      "VALUE_SETTING": null
    },
    {
      "dataForDataSets": [
        {
          "Data_Setting_Id": 291832,
          "DATASETVALUE": null,
          "DATA_SUMMARY_ID": 436377,
          "SKIP": 0,
          "STEPS_ID": 436444
        },
        {
          "Data_Setting_Id": 291834,
          "DATASETVALUE": null,
          "DATA_SUMMARY_ID": 436382,
          "SKIP": 0,
          "STEPS_ID": 436444
        },
        {
          "Data_Setting_Id": 291833,
          "DATASETVALUE": null,
          "DATA_SUMMARY_ID": 436378,
          "SKIP": 0,
          "STEPS_ID": 436444
        }
      ],
      "recordStatus": 0,
      "TEST_CASE_ID": 3086,
      "TEST_CASE_NAME": "Futures Trd Action Util",
      "KEY_WORD_ID": 14,
      "KEY_WORD_NAME": "MaximizeWindow",
      "OBJECT_HAPPY_NAME": "Summit Start",
      "OBJECT_ID": 32286,
      "OBJECT_TYPE": "Summit Start",
      "QUICK_ACCESS": "swfname:=Desktop|Page\nText:=^((Misys|Finastra ){0,1}(FusionCapital|Fusion ){0,1}(Markets ){0,1}Summit( FT){0,1})(?!(.*Login)).*\nswftypename:=Summit\\.Framework\\.Desktop\\.(Desktop|Page){1}\nindex:=0",
      "ENUM_TYPE": null,
      "APPLICATION_ID": 193,
      "OBJECT_NAME_ID": 24912,
      "TYPE_NAME": "Pegwindow",
      "STEPS_ID": 436444,
      "COLUMN_ROW_SETTING": null,
      "COMMENTINFO": null,
      "IS_RUNNABLE": null,
      "RUN_ORDER": 2,
      "VALUE_SETTING": null
    },
    {
      "dataForDataSets": [
        {
          "Data_Setting_Id": 291832,
          "DATASETVALUE": null,
          "DATA_SUMMARY_ID": 436377,
          "SKIP": 0,
          "STEPS_ID": 436444
        },
        {
          "Data_Setting_Id": 291834,
          "DATASETVALUE": null,
          "DATA_SUMMARY_ID": 436382,
          "SKIP": 0,
          "STEPS_ID": 436444
        },
        {
          "Data_Setting_Id": 291833,
          "DATASETVALUE": null,
          "DATA_SUMMARY_ID": 436378,
          "SKIP": 0,
          "STEPS_ID": 436444
        }
      ],
      "recordStatus": 0,
      "TEST_CASE_ID": 3086,
      "TEST_CASE_NAME": "Futures Trd Action Util",
      "KEY_WORD_ID": 14,
      "KEY_WORD_NAME": "MaximizeWindow",
      "OBJECT_HAPPY_NAME": "Summit Start",
      "OBJECT_ID": 40604,
      "OBJECT_TYPE": "Summit Start",
      "QUICK_ACCESS": "swfname:=Desktop|Page\nText:=^((Misys|Finastra ){0,1}(FusionCapital|Fusion ){0,1}(Markets ){0,1}Summit( FT){0,1})(?!(.*Login)).*\nswftypename:=Summit\\.Framework\\.Desktop\\.(Desktop|Page){1}\nindex:=0",
      "ENUM_TYPE": null,
      "APPLICATION_ID": 194,
      "OBJECT_NAME_ID": 24912,
      "TYPE_NAME": "Pegwindow",
      "STEPS_ID": 436444,
      "COLUMN_ROW_SETTING": null,
      "COMMENTINFO": null,
      "IS_RUNNABLE": null,
      "RUN_ORDER": 2,
      "VALUE_SETTING": null
    },
    {
      "dataForDataSets": [
        {
          "Data_Setting_Id": 291835,
          "DATASETVALUE": null,
          "DATA_SUMMARY_ID": 436377,
          "SKIP": 0,
          "STEPS_ID": 436445
        },
        {
          "Data_Setting_Id": 291837,
          "DATASETVALUE": null,
          "DATA_SUMMARY_ID": 436382,
          "SKIP": 0,
          "STEPS_ID": 436445
        },
        {
          "Data_Setting_Id": 291836,
          "DATASETVALUE": null,
          "DATA_SUMMARY_ID": 436378,
          "SKIP": 0,
          "STEPS_ID": 436445
        }
      ],
      "recordStatus": 0,
      "TEST_CASE_ID": 3086,
      "TEST_CASE_NAME": "Futures Trd Action Util",
      "KEY_WORD_ID": 12,
      "KEY_WORD_NAME": "LaunchApplication",
      "OBJECT_HAPPY_NAME": "ApplicationName",
      "OBJECT_ID": 35170,
      "OBJECT_TYPE": "Summit Start",
      "QUICK_ACCESS": "swfname:=_toolbarsDockAreaTop",
      "ENUM_TYPE": null,
      "APPLICATION_ID": 193,
      "OBJECT_NAME_ID": 29559,
      "TYPE_NAME": "SwfToolBar",
      "STEPS_ID": 436445,
      "COLUMN_ROW_SETTING": null,
      "COMMENTINFO": null,
      "IS_RUNNABLE": null,
      "RUN_ORDER": 3,
      "VALUE_SETTING": null
    },
    {
      "dataForDataSets": [
        {
          "Data_Setting_Id": 291835,
          "DATASETVALUE": null,
          "DATA_SUMMARY_ID": 436377,
          "SKIP": 0,
          "STEPS_ID": 436445
        },
        {
          "Data_Setting_Id": 291837,
          "DATASETVALUE": null,
          "DATA_SUMMARY_ID": 436382,
          "SKIP": 0,
          "STEPS_ID": 436445
        },
        {
          "Data_Setting_Id": 291836,
          "DATASETVALUE": null,
          "DATA_SUMMARY_ID": 436378,
          "SKIP": 0,
          "STEPS_ID": 436445
        }
      ],
      "recordStatus": 0,
      "TEST_CASE_ID": 3086,
      "TEST_CASE_NAME": "Futures Trd Action Util",
      "KEY_WORD_ID": 12,
      "KEY_WORD_NAME": "LaunchApplication",
      "OBJECT_HAPPY_NAME": "ApplicationName",
      "OBJECT_ID": 44673,
      "OBJECT_TYPE": "Summit Start",
      "QUICK_ACCESS": "swfname:=_toolbarsDockAreaTop",
      "ENUM_TYPE": null,
      "APPLICATION_ID": 194,
      "OBJECT_NAME_ID": 29559,
      "TYPE_NAME": "SwfToolBar",
      "STEPS_ID": 436445,
      "COLUMN_ROW_SETTING": null,
      "COMMENTINFO": null,
      "IS_RUNNABLE": null,
      "RUN_ORDER": 3,
      "VALUE_SETTING": null
    },
    {
      "dataForDataSets": [
        {
          "Data_Setting_Id": 291838,
          "DATASETVALUE": null,
          "DATA_SUMMARY_ID": 436377,
          "SKIP": 0,
          "STEPS_ID": 436446
        },
        {
          "Data_Setting_Id": 291840,
          "DATASETVALUE": null,
          "DATA_SUMMARY_ID": 436382,
          "SKIP": 0,
          "STEPS_ID": 436446
        },
        {
          "Data_Setting_Id": 291839,
          "DATASETVALUE": null,
          "DATA_SUMMARY_ID": 436378,
          "SKIP": 0,
          "STEPS_ID": 436446
        }
      ],
      "recordStatus": 0,
      "TEST_CASE_ID": 3086,
      "TEST_CASE_NAME": "Futures Trd Action Util",
      "KEY_WORD_ID": 37,
      "KEY_WORD_NAME": "WaitForSeconds",
      "OBJECT_HAPPY_NAME": null,
      "OBJECT_ID": -1,
      "OBJECT_TYPE": null,
      "QUICK_ACCESS": null,
      "ENUM_TYPE": null,
      "APPLICATION_ID": -1,
      "OBJECT_NAME_ID": -1,
      "TYPE_NAME": " ",
      "STEPS_ID": 436446,
      "COLUMN_ROW_SETTING": "F",
      "COMMENTINFO": null,
      "IS_RUNNABLE": null,
      "RUN_ORDER": 4,
      "VALUE_SETTING": null
    },
    {
      "dataForDataSets": [
        {
          "Data_Setting_Id": 291841,
          "DATASETVALUE": null,
          "DATA_SUMMARY_ID": 436377,
          "SKIP": 0,
          "STEPS_ID": 436447
        },
        {
          "Data_Setting_Id": 291843,
          "DATASETVALUE": null,
          "DATA_SUMMARY_ID": 436382,
          "SKIP": 0,
          "STEPS_ID": 436447
        },
        {
          "Data_Setting_Id": 291842,
          "DATASETVALUE": null,
          "DATA_SUMMARY_ID": 436378,
          "SKIP": 0,
          "STEPS_ID": 436447
        }
      ],
      "recordStatus": 0,
      "TEST_CASE_ID": 3086,
      "TEST_CASE_NAME": "Futures Trd Action Util",
      "KEY_WORD_ID": 15,
      "KEY_WORD_NAME": "PegWindow",
      "OBJECT_HAPPY_NAME": "TRADE_BLOTTER",
      "OBJECT_ID": 40275,
      "OBJECT_TYPE": "TRADE_BLOTTER",
      "QUICK_ACCESS": "is owned window:=False\nis child window:=False\nText:=^((Misys|Finastra ){0,1}(FusionCapital|Fusion ){0,1}(Markets ){0,1}Summit( FT){0,1})(?!(.*Login)).*",
      "ENUM_TYPE": null,
      "APPLICATION_ID": 193,
      "OBJECT_NAME_ID": 24876,
      "TYPE_NAME": "Pegwindow",
      "STEPS_ID": 436447,
      "COLUMN_ROW_SETTING": null,
      "COMMENTINFO": null,
      "IS_RUNNABLE": null,
      "RUN_ORDER": 5,
      "VALUE_SETTING": null
    },
    {
      "dataForDataSets": [
        {
          "Data_Setting_Id": 291841,
          "DATASETVALUE": null,
          "DATA_SUMMARY_ID": 436377,
          "SKIP": 0,
          "STEPS_ID": 436447
        },
        {
          "Data_Setting_Id": 291843,
          "DATASETVALUE": null,
          "DATA_SUMMARY_ID": 436382,
          "SKIP": 0,
          "STEPS_ID": 436447
        },
        {
          "Data_Setting_Id": 291842,
          "DATASETVALUE": null,
          "DATA_SUMMARY_ID": 436378,
          "SKIP": 0,
          "STEPS_ID": 436447
        }
      ],
      "recordStatus": 0,
      "TEST_CASE_ID": 3086,
      "TEST_CASE_NAME": "Futures Trd Action Util",
      "KEY_WORD_ID": 15,
      "KEY_WORD_NAME": "PegWindow",
      "OBJECT_HAPPY_NAME": "TRADE_BLOTTER",
      "OBJECT_ID": 48473,
      "OBJECT_TYPE": "TRADE_BLOTTER",
      "QUICK_ACCESS": "is owned window:=False\nis child window:=False\nText:=^((Misys|Finastra ){0,1}(FusionCapital|Fusion ){0,1}(Markets ){0,1}Summit( FT){0,1})(?!(.*Login)).*",
      "ENUM_TYPE": null,
      "APPLICATION_ID": 194,
      "OBJECT_NAME_ID": 24876,
      "TYPE_NAME": "Pegwindow",
      "STEPS_ID": 436447,
      "COLUMN_ROW_SETTING": null,
      "COMMENTINFO": null,
      "IS_RUNNABLE": null,
      "RUN_ORDER": 5,
      "VALUE_SETTING": null
    },
    {
      "dataForDataSets": [
        {
          "Data_Setting_Id": 291844,
          "DATASETVALUE": null,
          "DATA_SUMMARY_ID": 436377,
          "SKIP": 0,
          "STEPS_ID": 436448
        },
        {
          "Data_Setting_Id": 291846,
          "DATASETVALUE": null,
          "DATA_SUMMARY_ID": 436382,
          "SKIP": 0,
          "STEPS_ID": 436448
        },
        {
          "Data_Setting_Id": 291845,
          "DATASETVALUE": null,
          "DATA_SUMMARY_ID": 436378,
          "SKIP": 0,
          "STEPS_ID": 436448
        }
      ],
      "recordStatus": 0,
      "TEST_CASE_ID": 3086,
      "TEST_CASE_NAME": "Futures Trd Action Util",
      "KEY_WORD_ID": 10,
      "KEY_WORD_NAME": "FillEdit",
      "OBJECT_HAPPY_NAME": "TRADE_BLOTTER_TRADE_ID",
      "OBJECT_ID": 48372,
      "OBJECT_TYPE": "TRADE_BLOTTER",
      "QUICK_ACCESS": "swfname:=Trade_ID",
      "ENUM_TYPE": null,
      "APPLICATION_ID": 194,
      "OBJECT_NAME_ID": 30378,
      "TYPE_NAME": "SwfEdit",
      "STEPS_ID": 436448,
      "COLUMN_ROW_SETTING": null,
      "COMMENTINFO": null,
      "IS_RUNNABLE": null,
      "RUN_ORDER": 6,
      "VALUE_SETTING": null
    },
    {
      "dataForDataSets": [
        {
          "Data_Setting_Id": 291844,
          "DATASETVALUE": null,
          "DATA_SUMMARY_ID": 436377,
          "SKIP": 0,
          "STEPS_ID": 436448
        },
        {
          "Data_Setting_Id": 291846,
          "DATASETVALUE": null,
          "DATA_SUMMARY_ID": 436382,
          "SKIP": 0,
          "STEPS_ID": 436448
        },
        {
          "Data_Setting_Id": 291845,
          "DATASETVALUE": null,
          "DATA_SUMMARY_ID": 436378,
          "SKIP": 0,
          "STEPS_ID": 436448
        }
      ],
      "recordStatus": 0,
      "TEST_CASE_ID": 3086,
      "TEST_CASE_NAME": "Futures Trd Action Util",
      "KEY_WORD_ID": 10,
      "KEY_WORD_NAME": "FillEdit",
      "OBJECT_HAPPY_NAME": "TRADE_BLOTTER_TRADE_ID",
      "OBJECT_ID": 40205,
      "OBJECT_TYPE": "TRADE_BLOTTER",
      "QUICK_ACCESS": "swfname:=Trade_ID",
      "ENUM_TYPE": null,
      "APPLICATION_ID": 193,
      "OBJECT_NAME_ID": 30378,
      "TYPE_NAME": "SwfEdit",
      "STEPS_ID": 436448,
      "COLUMN_ROW_SETTING": null,
      "COMMENTINFO": null,
      "IS_RUNNABLE": null,
      "RUN_ORDER": 6,
      "VALUE_SETTING": null
    },
    {
      "dataForDataSets": [
        {
          "Data_Setting_Id": 291847,
          "DATASETVALUE": null,
          "DATA_SUMMARY_ID": 436377,
          "SKIP": 0,
          "STEPS_ID": 436449
        },
        {
          "Data_Setting_Id": 291849,
          "DATASETVALUE": null,
          "DATA_SUMMARY_ID": 436382,
          "SKIP": 0,
          "STEPS_ID": 436449
        },
        {
          "Data_Setting_Id": 291848,
          "DATASETVALUE": null,
          "DATA_SUMMARY_ID": 436378,
          "SKIP": 0,
          "STEPS_ID": 436449
        }
      ],
      "recordStatus": 0,
      "TEST_CASE_ID": 3086,
      "TEST_CASE_NAME": "Futures Trd Action Util",
      "KEY_WORD_ID": 10,
      "KEY_WORD_NAME": "FillEdit",
      "OBJECT_HAPPY_NAME": "TRADE_BLOTTER_TRADE_TYPE",
      "OBJECT_ID": 39456,
      "OBJECT_TYPE": "TRADE_BLOTTER",
      "QUICK_ACCESS": "swfname:=Trade_Type",
      "ENUM_TYPE": null,
      "APPLICATION_ID": 193,
      "OBJECT_NAME_ID": 32163,
      "TYPE_NAME": "SwfEdit",
      "STEPS_ID": 436449,
      "COLUMN_ROW_SETTING": null,
      "COMMENTINFO": null,
      "IS_RUNNABLE": null,
      "RUN_ORDER": 7,
      "VALUE_SETTING": null
    },
    {
      "dataForDataSets": [
        {
          "Data_Setting_Id": 291847,
          "DATASETVALUE": null,
          "DATA_SUMMARY_ID": 436377,
          "SKIP": 0,
          "STEPS_ID": 436449
        },
        {
          "Data_Setting_Id": 291849,
          "DATASETVALUE": null,
          "DATA_SUMMARY_ID": 436382,
          "SKIP": 0,
          "STEPS_ID": 436449
        },
        {
          "Data_Setting_Id": 291848,
          "DATASETVALUE": null,
          "DATA_SUMMARY_ID": 436378,
          "SKIP": 0,
          "STEPS_ID": 436449
        }
      ],
      "recordStatus": 0,
      "TEST_CASE_ID": 3086,
      "TEST_CASE_NAME": "Futures Trd Action Util",
      "KEY_WORD_ID": 10,
      "KEY_WORD_NAME": "FillEdit",
      "OBJECT_HAPPY_NAME": "TRADE_BLOTTER_TRADE_TYPE",
      "OBJECT_ID": 47586,
      "OBJECT_TYPE": "TRADE_BLOTTER",
      "QUICK_ACCESS": "swfname:=Trade_Type",
      "ENUM_TYPE": null,
      "APPLICATION_ID": 194,
      "OBJECT_NAME_ID": 32163,
      "TYPE_NAME": "SwfEdit",
      "STEPS_ID": 436449,
      "COLUMN_ROW_SETTING": null,
      "COMMENTINFO": null,
      "IS_RUNNABLE": null,
      "RUN_ORDER": 7,
      "VALUE_SETTING": null
    },
    {
      "dataForDataSets": [
        {
          "Data_Setting_Id": 291850,
          "DATASETVALUE": null,
          "DATA_SUMMARY_ID": 436377,
          "SKIP": 0,
          "STEPS_ID": 436450
        },
        {
          "Data_Setting_Id": 291852,
          "DATASETVALUE": null,
          "DATA_SUMMARY_ID": 436382,
          "SKIP": 0,
          "STEPS_ID": 436450
        },
        {
          "Data_Setting_Id": 291851,
          "DATASETVALUE": null,
          "DATA_SUMMARY_ID": 436378,
          "SKIP": 0,
          "STEPS_ID": 436450
        }
      ],
      "recordStatus": 0,
      "TEST_CASE_ID": 3086,
      "TEST_CASE_NAME": "Futures Trd Action Util",
      "KEY_WORD_ID": 4,
      "KEY_WORD_NAME": "ClickButton",
      "OBJECT_HAPPY_NAME": "TRADE_BLOTTER_APPLY",
      "OBJECT_ID": 39369,
      "OBJECT_TYPE": "TRADE_BLOTTER",
      "QUICK_ACCESS": "swfname:=butApply",
      "ENUM_TYPE": null,
      "APPLICATION_ID": 193,
      "OBJECT_NAME_ID": 25902,
      "TYPE_NAME": "SwfButton",
      "STEPS_ID": 436450,
      "COLUMN_ROW_SETTING": null,
      "COMMENTINFO": null,
      "IS_RUNNABLE": null,
      "RUN_ORDER": 8,
      "VALUE_SETTING": null
    },
    {
      "dataForDataSets": [
        {
          "Data_Setting_Id": 291850,
          "DATASETVALUE": null,
          "DATA_SUMMARY_ID": 436377,
          "SKIP": 0,
          "STEPS_ID": 436450
        },
        {
          "Data_Setting_Id": 291852,
          "DATASETVALUE": null,
          "DATA_SUMMARY_ID": 436382,
          "SKIP": 0,
          "STEPS_ID": 436450
        },
        {
          "Data_Setting_Id": 291851,
          "DATASETVALUE": null,
          "DATA_SUMMARY_ID": 436378,
          "SKIP": 0,
          "STEPS_ID": 436450
        }
      ],
      "recordStatus": 0,
      "TEST_CASE_ID": 3086,
      "TEST_CASE_NAME": "Futures Trd Action Util",
      "KEY_WORD_ID": 4,
      "KEY_WORD_NAME": "ClickButton",
      "OBJECT_HAPPY_NAME": "TRADE_BLOTTER_APPLY",
      "OBJECT_ID": 47546,
      "OBJECT_TYPE": "TRADE_BLOTTER",
      "QUICK_ACCESS": "swfname:=butApply",
      "ENUM_TYPE": null,
      "APPLICATION_ID": 194,
      "OBJECT_NAME_ID": 25902,
      "TYPE_NAME": "SwfButton",
      "STEPS_ID": 436450,
      "COLUMN_ROW_SETTING": null,
      "COMMENTINFO": null,
      "IS_RUNNABLE": null,
      "RUN_ORDER": 8,
      "VALUE_SETTING": null
    },
    {
      "dataForDataSets": [
        {
          "Data_Setting_Id": 291853,
          "DATASETVALUE": null,
          "DATA_SUMMARY_ID": 436377,
          "SKIP": 0,
          "STEPS_ID": 436451
        },
        {
          "Data_Setting_Id": 291855,
          "DATASETVALUE": null,
          "DATA_SUMMARY_ID": 436382,
          "SKIP": 0,
          "STEPS_ID": 436451
        },
        {
          "Data_Setting_Id": 291854,
          "DATASETVALUE": null,
          "DATA_SUMMARY_ID": 436378,
          "SKIP": 0,
          "STEPS_ID": 436451
        }
      ],
      "recordStatus": 0,
      "TEST_CASE_ID": 3086,
      "TEST_CASE_NAME": "Futures Trd Action Util",
      "KEY_WORD_ID": 78,
      "KEY_WORD_NAME": "SnapShot",
      "OBJECT_HAPPY_NAME": "TRADE_BLOTTER_PANEL",
      "OBJECT_ID": 48990,
      "OBJECT_TYPE": "TRADE_BLOTTER",
      "QUICK_ACCESS": "SwfName:=TradeBlotterView",
      "ENUM_TYPE": null,
      "APPLICATION_ID": 194,
      "OBJECT_NAME_ID": 48895,
      "TYPE_NAME": "SwfWindow",
      "STEPS_ID": 436451,
      "COLUMN_ROW_SETTING": null,
      "COMMENTINFO": null,
      "IS_RUNNABLE": null,
      "RUN_ORDER": 9,
      "VALUE_SETTING": null
    },
    {
      "dataForDataSets": [
        {
          "Data_Setting_Id": 291853,
          "DATASETVALUE": null,
          "DATA_SUMMARY_ID": 436377,
          "SKIP": 0,
          "STEPS_ID": 436451
        },
        {
          "Data_Setting_Id": 291855,
          "DATASETVALUE": null,
          "DATA_SUMMARY_ID": 436382,
          "SKIP": 0,
          "STEPS_ID": 436451
        },
        {
          "Data_Setting_Id": 291854,
          "DATASETVALUE": null,
          "DATA_SUMMARY_ID": 436378,
          "SKIP": 0,
          "STEPS_ID": 436451
        }
      ],
      "recordStatus": 0,
      "TEST_CASE_ID": 3086,
      "TEST_CASE_NAME": "Futures Trd Action Util",
      "KEY_WORD_ID": 78,
      "KEY_WORD_NAME": "SnapShot",
      "OBJECT_HAPPY_NAME": "TRADE_BLOTTER_PANEL",
      "OBJECT_ID": 48954,
      "OBJECT_TYPE": "TRADE_BLOTTER",
      "QUICK_ACCESS": "SwfName:=TradeBlotterView",
      "ENUM_TYPE": null,
      "APPLICATION_ID": 193,
      "OBJECT_NAME_ID": 48895,
      "TYPE_NAME": "SwfWindow",
      "STEPS_ID": 436451,
      "COLUMN_ROW_SETTING": null,
      "COMMENTINFO": null,
      "IS_RUNNABLE": null,
      "RUN_ORDER": 9,
      "VALUE_SETTING": null
    },
    {
      "dataForDataSets": [
        {
          "Data_Setting_Id": 291856,
          "DATASETVALUE": null,
          "DATA_SUMMARY_ID": 436377,
          "SKIP": 0,
          "STEPS_ID": 436452
        },
        {
          "Data_Setting_Id": 291858,
          "DATASETVALUE": null,
          "DATA_SUMMARY_ID": 436382,
          "SKIP": 0,
          "STEPS_ID": 436452
        },
        {
          "Data_Setting_Id": 291857,
          "DATASETVALUE": null,
          "DATA_SUMMARY_ID": 436378,
          "SKIP": 0,
          "STEPS_ID": 436452
        }
      ],
      "recordStatus": 0,
      "TEST_CASE_ID": 3086,
      "TEST_CASE_NAME": "Futures Trd Action Util",
      "KEY_WORD_ID": 37,
      "KEY_WORD_NAME": "WaitForSeconds",
      "OBJECT_HAPPY_NAME": null,
      "OBJECT_ID": -1,
      "OBJECT_TYPE": null,
      "QUICK_ACCESS": null,
      "ENUM_TYPE": null,
      "APPLICATION_ID": -1,
      "OBJECT_NAME_ID": -1,
      "TYPE_NAME": " ",
      "STEPS_ID": 436452,
      "COLUMN_ROW_SETTING": "F",
      "COMMENTINFO": null,
      "IS_RUNNABLE": null,
      "RUN_ORDER": 10,
      "VALUE_SETTING": null
    },
    {
      "dataForDataSets": [
        {
          "Data_Setting_Id": 291859,
          "DATASETVALUE": null,
          "DATA_SUMMARY_ID": 436377,
          "SKIP": 0,
          "STEPS_ID": 436453
        },
        {
          "Data_Setting_Id": 291861,
          "DATASETVALUE": null,
          "DATA_SUMMARY_ID": 436382,
          "SKIP": 0,
          "STEPS_ID": 436453
        },
        {
          "Data_Setting_Id": 291860,
          "DATASETVALUE": null,
          "DATA_SUMMARY_ID": 436378,
          "SKIP": 0,
          "STEPS_ID": 436453
        }
      ],
      "recordStatus": 0,
      "TEST_CASE_ID": 3086,
      "TEST_CASE_NAME": "Futures Trd Action Util",
      "KEY_WORD_ID": 15,
      "KEY_WORD_NAME": "PegWindow",
      "OBJECT_HAPPY_NAME": "TRADE_BLOTTER",
      "OBJECT_ID": 40275,
      "OBJECT_TYPE": "TRADE_BLOTTER",
      "QUICK_ACCESS": "is owned window:=False\nis child window:=False\nText:=^((Misys|Finastra ){0,1}(FusionCapital|Fusion ){0,1}(Markets ){0,1}Summit( FT){0,1})(?!(.*Login)).*",
      "ENUM_TYPE": null,
      "APPLICATION_ID": 193,
      "OBJECT_NAME_ID": 24876,
      "TYPE_NAME": "Pegwindow",
      "STEPS_ID": 436453,
      "COLUMN_ROW_SETTING": null,
      "COMMENTINFO": null,
      "IS_RUNNABLE": null,
      "RUN_ORDER": 11,
      "VALUE_SETTING": null
    },
    {
      "dataForDataSets": [
        {
          "Data_Setting_Id": 291859,
          "DATASETVALUE": null,
          "DATA_SUMMARY_ID": 436377,
          "SKIP": 0,
          "STEPS_ID": 436453
        },
        {
          "Data_Setting_Id": 291861,
          "DATASETVALUE": null,
          "DATA_SUMMARY_ID": 436382,
          "SKIP": 0,
          "STEPS_ID": 436453
        },
        {
          "Data_Setting_Id": 291860,
          "DATASETVALUE": null,
          "DATA_SUMMARY_ID": 436378,
          "SKIP": 0,
          "STEPS_ID": 436453
        }
      ],
      "recordStatus": 0,
      "TEST_CASE_ID": 3086,
      "TEST_CASE_NAME": "Futures Trd Action Util",
      "KEY_WORD_ID": 15,
      "KEY_WORD_NAME": "PegWindow",
      "OBJECT_HAPPY_NAME": "TRADE_BLOTTER",
      "OBJECT_ID": 48473,
      "OBJECT_TYPE": "TRADE_BLOTTER",
      "QUICK_ACCESS": "is owned window:=False\nis child window:=False\nText:=^((Misys|Finastra ){0,1}(FusionCapital|Fusion ){0,1}(Markets ){0,1}Summit( FT){0,1})(?!(.*Login)).*",
      "ENUM_TYPE": null,
      "APPLICATION_ID": 194,
      "OBJECT_NAME_ID": 24876,
      "TYPE_NAME": "Pegwindow",
      "STEPS_ID": 436453,
      "COLUMN_ROW_SETTING": null,
      "COMMENTINFO": null,
      "IS_RUNNABLE": null,
      "RUN_ORDER": 11,
      "VALUE_SETTING": null
    },
    {
      "dataForDataSets": [
        {
          "Data_Setting_Id": 291862,
          "DATASETVALUE": null,
          "DATA_SUMMARY_ID": 436377,
          "SKIP": 0,
          "STEPS_ID": 436454
        },
        {
          "Data_Setting_Id": 291864,
          "DATASETVALUE": null,
          "DATA_SUMMARY_ID": 436382,
          "SKIP": 0,
          "STEPS_ID": 436454
        },
        {
          "Data_Setting_Id": 291863,
          "DATASETVALUE": null,
          "DATA_SUMMARY_ID": 436378,
          "SKIP": 0,
          "STEPS_ID": 436454
        }
      ],
      "recordStatus": 0,
      "TEST_CASE_ID": 3086,
      "TEST_CASE_NAME": "Futures Trd Action Util",
      "KEY_WORD_ID": 32,
      "KEY_WORD_NAME": "SearchAndClick",
      "OBJECT_HAPPY_NAME": "TRADE_BLOTTER_TABLE",
      "OBJECT_ID": 34197,
      "OBJECT_TYPE": "TRADE_BLOTTER",
      "QUICK_ACCESS": "swfname:=_Spr",
      "ENUM_TYPE": null,
      "APPLICATION_ID": 193,
      "OBJECT_NAME_ID": 27806,
      "TYPE_NAME": "SwfTable",
      "STEPS_ID": 436454,
      "COLUMN_ROW_SETTING": "MarsAddins;Trade ID;Action:LEFT_DBL_CLICK",
      "COMMENTINFO": null,
      "IS_RUNNABLE": null,
      "RUN_ORDER": 12,
      "VALUE_SETTING": null
    },
    {
      "dataForDataSets": [
        {
          "Data_Setting_Id": 291862,
          "DATASETVALUE": null,
          "DATA_SUMMARY_ID": 436377,
          "SKIP": 0,
          "STEPS_ID": 436454
        },
        {
          "Data_Setting_Id": 291864,
          "DATASETVALUE": null,
          "DATA_SUMMARY_ID": 436382,
          "SKIP": 0,
          "STEPS_ID": 436454
        },
        {
          "Data_Setting_Id": 291863,
          "DATASETVALUE": null,
          "DATA_SUMMARY_ID": 436378,
          "SKIP": 0,
          "STEPS_ID": 436454
        }
      ],
      "recordStatus": 0,
      "TEST_CASE_ID": 3086,
      "TEST_CASE_NAME": "Futures Trd Action Util",
      "KEY_WORD_ID": 32,
      "KEY_WORD_NAME": "SearchAndClick",
      "OBJECT_HAPPY_NAME": "TRADE_BLOTTER_TABLE",
      "OBJECT_ID": 43746,
      "OBJECT_TYPE": "TRADE_BLOTTER",
      "QUICK_ACCESS": "swfname:=_Spr",
      "ENUM_TYPE": null,
      "APPLICATION_ID": 194,
      "OBJECT_NAME_ID": 27806,
      "TYPE_NAME": "SwfTable",
      "STEPS_ID": 436454,
      "COLUMN_ROW_SETTING": "MarsAddins;Trade ID;Action:LEFT_DBL_CLICK",
      "COMMENTINFO": null,
      "IS_RUNNABLE": null,
      "RUN_ORDER": 12,
      "VALUE_SETTING": null
    },
    {
      "dataForDataSets": [
        {
          "Data_Setting_Id": 291865,
          "DATASETVALUE": null,
          "DATA_SUMMARY_ID": 436377,
          "SKIP": 0,
          "STEPS_ID": 436455
        },
        {
          "Data_Setting_Id": 291867,
          "DATASETVALUE": null,
          "DATA_SUMMARY_ID": 436382,
          "SKIP": 0,
          "STEPS_ID": 436455
        },
        {
          "Data_Setting_Id": 291866,
          "DATASETVALUE": null,
          "DATA_SUMMARY_ID": 436378,
          "SKIP": 0,
          "STEPS_ID": 436455
        }
      ],
      "recordStatus": 0,
      "TEST_CASE_ID": 3086,
      "TEST_CASE_NAME": "Futures Trd Action Util",
      "KEY_WORD_ID": 78,
      "KEY_WORD_NAME": "SnapShot",
      "OBJECT_HAPPY_NAME": "TRADE_BLOTTER_PANEL",
      "OBJECT_ID": 48990,
      "OBJECT_TYPE": "TRADE_BLOTTER",
      "QUICK_ACCESS": "SwfName:=TradeBlotterView",
      "ENUM_TYPE": null,
      "APPLICATION_ID": 194,
      "OBJECT_NAME_ID": 48895,
      "TYPE_NAME": "SwfWindow",
      "STEPS_ID": 436455,
      "COLUMN_ROW_SETTING": null,
      "COMMENTINFO": null,
      "IS_RUNNABLE": null,
      "RUN_ORDER": 13,
      "VALUE_SETTING": null
    },
    {
      "dataForDataSets": [
        {
          "Data_Setting_Id": 291865,
          "DATASETVALUE": null,
          "DATA_SUMMARY_ID": 436377,
          "SKIP": 0,
          "STEPS_ID": 436455
        },
        {
          "Data_Setting_Id": 291867,
          "DATASETVALUE": null,
          "DATA_SUMMARY_ID": 436382,
          "SKIP": 0,
          "STEPS_ID": 436455
        },
        {
          "Data_Setting_Id": 291866,
          "DATASETVALUE": null,
          "DATA_SUMMARY_ID": 436378,
          "SKIP": 0,
          "STEPS_ID": 436455
        }
      ],
      "recordStatus": 0,
      "TEST_CASE_ID": 3086,
      "TEST_CASE_NAME": "Futures Trd Action Util",
      "KEY_WORD_ID": 78,
      "KEY_WORD_NAME": "SnapShot",
      "OBJECT_HAPPY_NAME": "TRADE_BLOTTER_PANEL",
      "OBJECT_ID": 48954,
      "OBJECT_TYPE": "TRADE_BLOTTER",
      "QUICK_ACCESS": "SwfName:=TradeBlotterView",
      "ENUM_TYPE": null,
      "APPLICATION_ID": 193,
      "OBJECT_NAME_ID": 48895,
      "TYPE_NAME": "SwfWindow",
      "STEPS_ID": 436455,
      "COLUMN_ROW_SETTING": null,
      "COMMENTINFO": null,
      "IS_RUNNABLE": null,
      "RUN_ORDER": 13,
      "VALUE_SETTING": null
    },
    {
      "dataForDataSets": [
        {
          "Data_Setting_Id": 291868,
          "DATASETVALUE": null,
          "DATA_SUMMARY_ID": 436377,
          "SKIP": 0,
          "STEPS_ID": 436456
        },
        {
          "Data_Setting_Id": 291870,
          "DATASETVALUE": null,
          "DATA_SUMMARY_ID": 436382,
          "SKIP": 0,
          "STEPS_ID": 436456
        },
        {
          "Data_Setting_Id": 291869,
          "DATASETVALUE": null,
          "DATA_SUMMARY_ID": 436378,
          "SKIP": 0,
          "STEPS_ID": 436456
        }
      ],
      "recordStatus": 0,
      "TEST_CASE_ID": 3086,
      "TEST_CASE_NAME": "Futures Trd Action Util",
      "KEY_WORD_ID": 37,
      "KEY_WORD_NAME": "WaitForSeconds",
      "OBJECT_HAPPY_NAME": null,
      "OBJECT_ID": -1,
      "OBJECT_TYPE": null,
      "QUICK_ACCESS": null,
      "ENUM_TYPE": null,
      "APPLICATION_ID": -1,
      "OBJECT_NAME_ID": -1,
      "TYPE_NAME": " ",
      "STEPS_ID": 436456,
      "COLUMN_ROW_SETTING": "F",
      "COMMENTINFO": null,
      "IS_RUNNABLE": null,
      "RUN_ORDER": 14,
      "VALUE_SETTING": null
    },
    {
      "dataForDataSets": [
        {
          "Data_Setting_Id": 291871,
          "DATASETVALUE": null,
          "DATA_SUMMARY_ID": 436377,
          "SKIP": 0,
          "STEPS_ID": 436457
        },
        {
          "Data_Setting_Id": 291873,
          "DATASETVALUE": null,
          "DATA_SUMMARY_ID": 436382,
          "SKIP": 0,
          "STEPS_ID": 436457
        },
        {
          "Data_Setting_Id": 291872,
          "DATASETVALUE": null,
          "DATA_SUMMARY_ID": 436378,
          "SKIP": 0,
          "STEPS_ID": 436457
        }
      ],
      "recordStatus": 0,
      "TEST_CASE_ID": 3086,
      "TEST_CASE_NAME": "Futures Trd Action Util",
      "KEY_WORD_ID": 15,
      "KEY_WORD_NAME": "PegWindow",
      "OBJECT_HAPPY_NAME": "FUTURES_TRADE",
      "OBJECT_ID": 34218,
      "OBJECT_TYPE": "FUTURES_TRADE",
      "QUICK_ACCESS": "is owned window:=False\nis child window:=False\ntext:=((Finastra ){0,1}(Fusion ){0,1}(Markets ){0,1}Summit( FT){0,1})(?!(.*Login)).*",
      "ENUM_TYPE": null,
      "APPLICATION_ID": 193,
      "OBJECT_NAME_ID": 24856,
      "TYPE_NAME": "Pegwindow",
      "STEPS_ID": 436457,
      "COLUMN_ROW_SETTING": null,
      "COMMENTINFO": null,
      "IS_RUNNABLE": null,
      "RUN_ORDER": 15,
      "VALUE_SETTING": null
    },
    {
      "dataForDataSets": [
        {
          "Data_Setting_Id": 291871,
          "DATASETVALUE": null,
          "DATA_SUMMARY_ID": 436377,
          "SKIP": 0,
          "STEPS_ID": 436457
        },
        {
          "Data_Setting_Id": 291873,
          "DATASETVALUE": null,
          "DATA_SUMMARY_ID": 436382,
          "SKIP": 0,
          "STEPS_ID": 436457
        },
        {
          "Data_Setting_Id": 291872,
          "DATASETVALUE": null,
          "DATA_SUMMARY_ID": 436378,
          "SKIP": 0,
          "STEPS_ID": 436457
        }
      ],
      "recordStatus": 0,
      "TEST_CASE_ID": 3086,
      "TEST_CASE_NAME": "Futures Trd Action Util",
      "KEY_WORD_ID": 15,
      "KEY_WORD_NAME": "PegWindow",
      "OBJECT_HAPPY_NAME": "FUTURES_TRADE",
      "OBJECT_ID": 43767,
      "OBJECT_TYPE": "FUTURES_TRADE",
      "QUICK_ACCESS": "is owned window:=False\nis child window:=False\ntext:=((Finastra ){0,1}(Fusion ){0,1}(Markets ){0,1}Summit( FT){0,1})(?!(.*Login)).*",
      "ENUM_TYPE": null,
      "APPLICATION_ID": 194,
      "OBJECT_NAME_ID": 24856,
      "TYPE_NAME": "Pegwindow",
      "STEPS_ID": 436457,
      "COLUMN_ROW_SETTING": null,
      "COMMENTINFO": null,
      "IS_RUNNABLE": null,
      "RUN_ORDER": 15,
      "VALUE_SETTING": null
    },
    {
      "dataForDataSets": [
        {
          "Data_Setting_Id": 291874,
          "DATASETVALUE": null,
          "DATA_SUMMARY_ID": 436377,
          "SKIP": 0,
          "STEPS_ID": 436458
        },
        {
          "Data_Setting_Id": 291876,
          "DATASETVALUE": null,
          "DATA_SUMMARY_ID": 436382,
          "SKIP": 0,
          "STEPS_ID": 436458
        },
        {
          "Data_Setting_Id": 291875,
          "DATASETVALUE": null,
          "DATA_SUMMARY_ID": 436378,
          "SKIP": 0,
          "STEPS_ID": 436458
        }
      ],
      "recordStatus": 0,
      "TEST_CASE_ID": 3086,
      "TEST_CASE_NAME": "Futures Trd Action Util",
      "KEY_WORD_ID": 14,
      "KEY_WORD_NAME": "MaximizeWindow",
      "OBJECT_HAPPY_NAME": "FUTURES_TRADE",
      "OBJECT_ID": 34218,
      "OBJECT_TYPE": "FUTURES_TRADE",
      "QUICK_ACCESS": "is owned window:=False\nis child window:=False\ntext:=((Finastra ){0,1}(Fusion ){0,1}(Markets ){0,1}Summit( FT){0,1})(?!(.*Login)).*",
      "ENUM_TYPE": null,
      "APPLICATION_ID": 193,
      "OBJECT_NAME_ID": 24856,
      "TYPE_NAME": "Pegwindow",
      "STEPS_ID": 436458,
      "COLUMN_ROW_SETTING": null,
      "COMMENTINFO": null,
      "IS_RUNNABLE": null,
      "RUN_ORDER": 16,
      "VALUE_SETTING": null
    },
    {
      "dataForDataSets": [
        {
          "Data_Setting_Id": 291874,
          "DATASETVALUE": null,
          "DATA_SUMMARY_ID": 436377,
          "SKIP": 0,
          "STEPS_ID": 436458
        },
        {
          "Data_Setting_Id": 291876,
          "DATASETVALUE": null,
          "DATA_SUMMARY_ID": 436382,
          "SKIP": 0,
          "STEPS_ID": 436458
        },
        {
          "Data_Setting_Id": 291875,
          "DATASETVALUE": null,
          "DATA_SUMMARY_ID": 436378,
          "SKIP": 0,
          "STEPS_ID": 436458
        }
      ],
      "recordStatus": 0,
      "TEST_CASE_ID": 3086,
      "TEST_CASE_NAME": "Futures Trd Action Util",
      "KEY_WORD_ID": 14,
      "KEY_WORD_NAME": "MaximizeWindow",
      "OBJECT_HAPPY_NAME": "FUTURES_TRADE",
      "OBJECT_ID": 43767,
      "OBJECT_TYPE": "FUTURES_TRADE",
      "QUICK_ACCESS": "is owned window:=False\nis child window:=False\ntext:=((Finastra ){0,1}(Fusion ){0,1}(Markets ){0,1}Summit( FT){0,1})(?!(.*Login)).*",
      "ENUM_TYPE": null,
      "APPLICATION_ID": 194,
      "OBJECT_NAME_ID": 24856,
      "TYPE_NAME": "Pegwindow",
      "STEPS_ID": 436458,
      "COLUMN_ROW_SETTING": null,
      "COMMENTINFO": null,
      "IS_RUNNABLE": null,
      "RUN_ORDER": 16,
      "VALUE_SETTING": null
    },
    {
      "dataForDataSets": [
        {
          "Data_Setting_Id": 291877,
          "DATASETVALUE": null,
          "DATA_SUMMARY_ID": 436377,
          "SKIP": 0,
          "STEPS_ID": 436459
        },
        {
          "Data_Setting_Id": 291879,
          "DATASETVALUE": null,
          "DATA_SUMMARY_ID": 436382,
          "SKIP": 0,
          "STEPS_ID": 436459
        },
        {
          "Data_Setting_Id": 291878,
          "DATASETVALUE": null,
          "DATA_SUMMARY_ID": 436378,
          "SKIP": 0,
          "STEPS_ID": 436459
        }
      ],
      "recordStatus": 0,
      "TEST_CASE_ID": 3086,
      "TEST_CASE_NAME": "Futures Trd Action Util",
      "KEY_WORD_ID": 37,
      "KEY_WORD_NAME": "WaitForSeconds",
      "OBJECT_HAPPY_NAME": null,
      "OBJECT_ID": -1,
      "OBJECT_TYPE": null,
      "QUICK_ACCESS": null,
      "ENUM_TYPE": null,
      "APPLICATION_ID": -1,
      "OBJECT_NAME_ID": -1,
      "TYPE_NAME": " ",
      "STEPS_ID": 436459,
      "COLUMN_ROW_SETTING": null,
      "COMMENTINFO": null,
      "IS_RUNNABLE": null,
      "RUN_ORDER": 17,
      "VALUE_SETTING": null
    },
    {
      "dataForDataSets": [
        {
          "Data_Setting_Id": 291880,
          "DATASETVALUE": null,
          "DATA_SUMMARY_ID": 436377,
          "SKIP": 0,
          "STEPS_ID": 436460
        },
        {
          "Data_Setting_Id": 291882,
          "DATASETVALUE": null,
          "DATA_SUMMARY_ID": 436382,
          "SKIP": 0,
          "STEPS_ID": 436460
        },
        {
          "Data_Setting_Id": 291881,
          "DATASETVALUE": null,
          "DATA_SUMMARY_ID": 436378,
          "SKIP": 0,
          "STEPS_ID": 436460
        }
      ],
      "recordStatus": 0,
      "TEST_CASE_ID": 3086,
      "TEST_CASE_NAME": "Futures Trd Action Util",
      "KEY_WORD_ID": 26,
      "KEY_WORD_NAME": "VerifyValue",
      "OBJECT_HAPPY_NAME": "FUTURES_STATE",
      "OBJECT_ID": 45294,
      "OBJECT_TYPE": "FUTURES_TRADE",
      "QUICK_ACCESS": "swfname:=_stateLLControl",
      "ENUM_TYPE": null,
      "APPLICATION_ID": 194,
      "OBJECT_NAME_ID": 27405,
      "TYPE_NAME": "SwfLabel",
      "STEPS_ID": 436460,
      "COLUMN_ROW_SETTING": null,
      "COMMENTINFO": null,
      "IS_RUNNABLE": null,
      "RUN_ORDER": 18,
      "VALUE_SETTING": null
    },
    {
      "dataForDataSets": [
        {
          "Data_Setting_Id": 291880,
          "DATASETVALUE": null,
          "DATA_SUMMARY_ID": 436377,
          "SKIP": 0,
          "STEPS_ID": 436460
        },
        {
          "Data_Setting_Id": 291882,
          "DATASETVALUE": null,
          "DATA_SUMMARY_ID": 436382,
          "SKIP": 0,
          "STEPS_ID": 436460
        },
        {
          "Data_Setting_Id": 291881,
          "DATASETVALUE": null,
          "DATA_SUMMARY_ID": 436378,
          "SKIP": 0,
          "STEPS_ID": 436460
        }
      ],
      "recordStatus": 0,
      "TEST_CASE_ID": 3086,
      "TEST_CASE_NAME": "Futures Trd Action Util",
      "KEY_WORD_ID": 26,
      "KEY_WORD_NAME": "VerifyValue",
      "OBJECT_HAPPY_NAME": "FUTURES_STATE",
      "OBJECT_ID": 36365,
      "OBJECT_TYPE": "FUTURES_TRADE",
      "QUICK_ACCESS": "swfname:=_stateLLControl",
      "ENUM_TYPE": null,
      "APPLICATION_ID": 193,
      "OBJECT_NAME_ID": 27405,
      "TYPE_NAME": "SwfLabel",
      "STEPS_ID": 436460,
      "COLUMN_ROW_SETTING": null,
      "COMMENTINFO": null,
      "IS_RUNNABLE": null,
      "RUN_ORDER": 18,
      "VALUE_SETTING": null
    },
    {
      "dataForDataSets": [
        {
          "Data_Setting_Id": 291883,
          "DATASETVALUE": null,
          "DATA_SUMMARY_ID": 436377,
          "SKIP": 0,
          "STEPS_ID": 436461
        },
        {
          "Data_Setting_Id": 291885,
          "DATASETVALUE": null,
          "DATA_SUMMARY_ID": 436382,
          "SKIP": 0,
          "STEPS_ID": 436461
        },
        {
          "Data_Setting_Id": 291884,
          "DATASETVALUE": null,
          "DATA_SUMMARY_ID": 436378,
          "SKIP": 0,
          "STEPS_ID": 436461
        }
      ],
      "recordStatus": 0,
      "TEST_CASE_ID": 3086,
      "TEST_CASE_NAME": "Futures Trd Action Util",
      "KEY_WORD_ID": 22,
      "KEY_WORD_NAME": "SelectMenuItem",
      "OBJECT_HAPPY_NAME": null,
      "OBJECT_ID": -1,
      "OBJECT_TYPE": null,
      "QUICK_ACCESS": null,
      "ENUM_TYPE": null,
      "APPLICATION_ID": -1,
      "OBJECT_NAME_ID": -1,
      "TYPE_NAME": " ",
      "STEPS_ID": 436461,
      "COLUMN_ROW_SETTING": null,
      "COMMENTINFO": null,
      "IS_RUNNABLE": null,
      "RUN_ORDER": 19,
      "VALUE_SETTING": null
    },
    {
      "dataForDataSets": [
        {
          "Data_Setting_Id": 291886,
          "DATASETVALUE": null,
          "DATA_SUMMARY_ID": 436377,
          "SKIP": 0,
          "STEPS_ID": 436462
        },
        {
          "Data_Setting_Id": 291888,
          "DATASETVALUE": null,
          "DATA_SUMMARY_ID": 436382,
          "SKIP": 0,
          "STEPS_ID": 436462
        },
        {
          "Data_Setting_Id": 291887,
          "DATASETVALUE": null,
          "DATA_SUMMARY_ID": 436378,
          "SKIP": 0,
          "STEPS_ID": 436462
        }
      ],
      "recordStatus": 0,
      "TEST_CASE_ID": 3086,
      "TEST_CASE_NAME": "Futures Trd Action Util",
      "KEY_WORD_ID": 37,
      "KEY_WORD_NAME": "WaitForSeconds",
      "OBJECT_HAPPY_NAME": null,
      "OBJECT_ID": -1,
      "OBJECT_TYPE": null,
      "QUICK_ACCESS": null,
      "ENUM_TYPE": null,
      "APPLICATION_ID": -1,
      "OBJECT_NAME_ID": -1,
      "TYPE_NAME": " ",
      "STEPS_ID": 436462,
      "COLUMN_ROW_SETTING": null,
      "COMMENTINFO": null,
      "IS_RUNNABLE": null,
      "RUN_ORDER": 20,
      "VALUE_SETTING": null
    },
    {
      "dataForDataSets": [
        {
          "Data_Setting_Id": 291889,
          "DATASETVALUE": null,
          "DATA_SUMMARY_ID": 436377,
          "SKIP": 0,
          "STEPS_ID": 436463
        },
        {
          "Data_Setting_Id": 291891,
          "DATASETVALUE": null,
          "DATA_SUMMARY_ID": 436382,
          "SKIP": 0,
          "STEPS_ID": 436463
        },
        {
          "Data_Setting_Id": 291890,
          "DATASETVALUE": null,
          "DATA_SUMMARY_ID": 436378,
          "SKIP": 0,
          "STEPS_ID": 436463
        }
      ],
      "recordStatus": 0,
      "TEST_CASE_ID": 3086,
      "TEST_CASE_NAME": "Futures Trd Action Util",
      "KEY_WORD_ID": 77,
      "KEY_WORD_NAME": "CaptureAndCompare",
      "OBJECT_HAPPY_NAME": "FUTURES_STATE",
      "OBJECT_ID": 45294,
      "OBJECT_TYPE": "FUTURES_TRADE",
      "QUICK_ACCESS": "swfname:=_stateLLControl",
      "ENUM_TYPE": null,
      "APPLICATION_ID": 194,
      "OBJECT_NAME_ID": 27405,
      "TYPE_NAME": "SwfLabel",
      "STEPS_ID": 436463,
      "COLUMN_ROW_SETTING": null,
      "COMMENTINFO": null,
      "IS_RUNNABLE": null,
      "RUN_ORDER": 21,
      "VALUE_SETTING": null
    },
    {
      "dataForDataSets": [
        {
          "Data_Setting_Id": 291889,
          "DATASETVALUE": null,
          "DATA_SUMMARY_ID": 436377,
          "SKIP": 0,
          "STEPS_ID": 436463
        },
        {
          "Data_Setting_Id": 291891,
          "DATASETVALUE": null,
          "DATA_SUMMARY_ID": 436382,
          "SKIP": 0,
          "STEPS_ID": 436463
        },
        {
          "Data_Setting_Id": 291890,
          "DATASETVALUE": null,
          "DATA_SUMMARY_ID": 436378,
          "SKIP": 0,
          "STEPS_ID": 436463
        }
      ],
      "recordStatus": 0,
      "TEST_CASE_ID": 3086,
      "TEST_CASE_NAME": "Futures Trd Action Util",
      "KEY_WORD_ID": 77,
      "KEY_WORD_NAME": "CaptureAndCompare",
      "OBJECT_HAPPY_NAME": "FUTURES_STATE",
      "OBJECT_ID": 36365,
      "OBJECT_TYPE": "FUTURES_TRADE",
      "QUICK_ACCESS": "swfname:=_stateLLControl",
      "ENUM_TYPE": null,
      "APPLICATION_ID": 193,
      "OBJECT_NAME_ID": 27405,
      "TYPE_NAME": "SwfLabel",
      "STEPS_ID": 436463,
      "COLUMN_ROW_SETTING": null,
      "COMMENTINFO": null,
      "IS_RUNNABLE": null,
      "RUN_ORDER": 21,
      "VALUE_SETTING": null
    },
    {
      "dataForDataSets": [
        {
          "Data_Setting_Id": 291892,
          "DATASETVALUE": null,
          "DATA_SUMMARY_ID": 436377,
          "SKIP": 0,
          "STEPS_ID": 436464
        },
        {
          "Data_Setting_Id": 291894,
          "DATASETVALUE": null,
          "DATA_SUMMARY_ID": 436382,
          "SKIP": 0,
          "STEPS_ID": 436464
        },
        {
          "Data_Setting_Id": 291893,
          "DATASETVALUE": null,
          "DATA_SUMMARY_ID": 436378,
          "SKIP": 0,
          "STEPS_ID": 436464
        }
      ],
      "recordStatus": 0,
      "TEST_CASE_ID": 3086,
      "TEST_CASE_NAME": "Futures Trd Action Util",
      "KEY_WORD_ID": 78,
      "KEY_WORD_NAME": "SnapShot",
      "OBJECT_HAPPY_NAME": "FUTURES_TRADE_PANEL",
      "OBJECT_ID": 49031,
      "OBJECT_TYPE": "FUTURES_TRADE",
      "QUICK_ACCESS": "swfname:=FuturesTradeView",
      "ENUM_TYPE": null,
      "APPLICATION_ID": 193,
      "OBJECT_NAME_ID": 49026,
      "TYPE_NAME": "SwfWindow",
      "STEPS_ID": 436464,
      "COLUMN_ROW_SETTING": null,
      "COMMENTINFO": null,
      "IS_RUNNABLE": null,
      "RUN_ORDER": 22,
      "VALUE_SETTING": null
    },
    {
      "dataForDataSets": [
        {
          "Data_Setting_Id": 291892,
          "DATASETVALUE": null,
          "DATA_SUMMARY_ID": 436377,
          "SKIP": 0,
          "STEPS_ID": 436464
        },
        {
          "Data_Setting_Id": 291894,
          "DATASETVALUE": null,
          "DATA_SUMMARY_ID": 436382,
          "SKIP": 0,
          "STEPS_ID": 436464
        },
        {
          "Data_Setting_Id": 291893,
          "DATASETVALUE": null,
          "DATA_SUMMARY_ID": 436378,
          "SKIP": 0,
          "STEPS_ID": 436464
        }
      ],
      "recordStatus": 0,
      "TEST_CASE_ID": 3086,
      "TEST_CASE_NAME": "Futures Trd Action Util",
      "KEY_WORD_ID": 78,
      "KEY_WORD_NAME": "SnapShot",
      "OBJECT_HAPPY_NAME": "FUTURES_TRADE_PANEL",
      "OBJECT_ID": 49049,
      "OBJECT_TYPE": "FUTURES_TRADE",
      "QUICK_ACCESS": "swfname:=FuturesTradeView",
      "ENUM_TYPE": null,
      "APPLICATION_ID": 194,
      "OBJECT_NAME_ID": 49026,
      "TYPE_NAME": "SwfWindow",
      "STEPS_ID": 436464,
      "COLUMN_ROW_SETTING": null,
      "COMMENTINFO": null,
      "IS_RUNNABLE": null,
      "RUN_ORDER": 22,
      "VALUE_SETTING": null
    },
    {
      "dataForDataSets": [
        {
          "Data_Setting_Id": 291895,
          "DATASETVALUE": null,
          "DATA_SUMMARY_ID": 436377,
          "SKIP": 0,
          "STEPS_ID": 436465
        },
        {
          "Data_Setting_Id": 291897,
          "DATASETVALUE": null,
          "DATA_SUMMARY_ID": 436382,
          "SKIP": 0,
          "STEPS_ID": 436465
        },
        {
          "Data_Setting_Id": 291896,
          "DATASETVALUE": null,
          "DATA_SUMMARY_ID": 436378,
          "SKIP": 0,
          "STEPS_ID": 436465
        }
      ],
      "recordStatus": 0,
      "TEST_CASE_ID": 3086,
      "TEST_CASE_NAME": "Futures Trd Action Util",
      "KEY_WORD_ID": 3,
      "KEY_WORD_NAME": "CheckError",
      "OBJECT_HAPPY_NAME": null,
      "OBJECT_ID": -1,
      "OBJECT_TYPE": null,
      "QUICK_ACCESS": null,
      "ENUM_TYPE": null,
      "APPLICATION_ID": -1,
      "OBJECT_NAME_ID": -1,
      "TYPE_NAME": " ",
      "STEPS_ID": 436465,
      "COLUMN_ROW_SETTING": null,
      "COMMENTINFO": null,
      "IS_RUNNABLE": null,
      "RUN_ORDER": 23,
      "VALUE_SETTING": null
    },
    {
      "dataForDataSets": [
        {
          "Data_Setting_Id": 291898,
          "DATASETVALUE": null,
          "DATA_SUMMARY_ID": 436377,
          "SKIP": 0,
          "STEPS_ID": 436466
        },
        {
          "Data_Setting_Id": 291900,
          "DATASETVALUE": null,
          "DATA_SUMMARY_ID": 436382,
          "SKIP": 0,
          "STEPS_ID": 436466
        },
        {
          "Data_Setting_Id": 291899,
          "DATASETVALUE": null,
          "DATA_SUMMARY_ID": 436378,
          "SKIP": 0,
          "STEPS_ID": 436466
        }
      ],
      "recordStatus": 0,
      "TEST_CASE_ID": 3086,
      "TEST_CASE_NAME": "Futures Trd Action Util",
      "KEY_WORD_ID": 15,
      "KEY_WORD_NAME": "PegWindow",
      "OBJECT_HAPPY_NAME": "Summit Start",
      "OBJECT_ID": 32286,
      "OBJECT_TYPE": "Summit Start",
      "QUICK_ACCESS": "swfname:=Desktop|Page\nText:=^((Misys|Finastra ){0,1}(FusionCapital|Fusion ){0,1}(Markets ){0,1}Summit( FT){0,1})(?!(.*Login)).*\nswftypename:=Summit\\.Framework\\.Desktop\\.(Desktop|Page){1}\nindex:=0",
      "ENUM_TYPE": null,
      "APPLICATION_ID": 193,
      "OBJECT_NAME_ID": 24912,
      "TYPE_NAME": "Pegwindow",
      "STEPS_ID": 436466,
      "COLUMN_ROW_SETTING": null,
      "COMMENTINFO": null,
      "IS_RUNNABLE": null,
      "RUN_ORDER": 24,
      "VALUE_SETTING": null
    },
    {
      "dataForDataSets": [
        {
          "Data_Setting_Id": 291898,
          "DATASETVALUE": null,
          "DATA_SUMMARY_ID": 436377,
          "SKIP": 0,
          "STEPS_ID": 436466
        },
        {
          "Data_Setting_Id": 291900,
          "DATASETVALUE": null,
          "DATA_SUMMARY_ID": 436382,
          "SKIP": 0,
          "STEPS_ID": 436466
        },
        {
          "Data_Setting_Id": 291899,
          "DATASETVALUE": null,
          "DATA_SUMMARY_ID": 436378,
          "SKIP": 0,
          "STEPS_ID": 436466
        }
      ],
      "recordStatus": 0,
      "TEST_CASE_ID": 3086,
      "TEST_CASE_NAME": "Futures Trd Action Util",
      "KEY_WORD_ID": 15,
      "KEY_WORD_NAME": "PegWindow",
      "OBJECT_HAPPY_NAME": "Summit Start",
      "OBJECT_ID": 40604,
      "OBJECT_TYPE": "Summit Start",
      "QUICK_ACCESS": "swfname:=Desktop|Page\nText:=^((Misys|Finastra ){0,1}(FusionCapital|Fusion ){0,1}(Markets ){0,1}Summit( FT){0,1})(?!(.*Login)).*\nswftypename:=Summit\\.Framework\\.Desktop\\.(Desktop|Page){1}\nindex:=0",
      "ENUM_TYPE": null,
      "APPLICATION_ID": 194,
      "OBJECT_NAME_ID": 24912,
      "TYPE_NAME": "Pegwindow",
      "STEPS_ID": 436466,
      "COLUMN_ROW_SETTING": null,
      "COMMENTINFO": null,
      "IS_RUNNABLE": null,
      "RUN_ORDER": 24,
      "VALUE_SETTING": null
    },
    {
      "dataForDataSets": [
        {
          "Data_Setting_Id": 291901,
          "DATASETVALUE": null,
          "DATA_SUMMARY_ID": 436377,
          "SKIP": 0,
          "STEPS_ID": 436467
        },
        {
          "Data_Setting_Id": 291903,
          "DATASETVALUE": null,
          "DATA_SUMMARY_ID": 436382,
          "SKIP": 0,
          "STEPS_ID": 436467
        },
        {
          "Data_Setting_Id": 291902,
          "DATASETVALUE": null,
          "DATA_SUMMARY_ID": 436378,
          "SKIP": 0,
          "STEPS_ID": 436467
        }
      ],
      "recordStatus": 0,
      "TEST_CASE_ID": 3086,
      "TEST_CASE_NAME": "Futures Trd Action Util",
      "KEY_WORD_ID": 4,
      "KEY_WORD_NAME": "ClickButton",
      "OBJECT_HAPPY_NAME": "CLOSE_BUTTON",
      "OBJECT_ID": 32409,
      "OBJECT_TYPE": "Summit Start",
      "QUICK_ACCESS": "swfname:=_closeButton\nswftypename:=Summit.Framework.DesktopContent.ImageButton\nindex:=0",
      "ENUM_TYPE": null,
      "APPLICATION_ID": 193,
      "OBJECT_NAME_ID": 30430,
      "TYPE_NAME": "SwfButton",
      "STEPS_ID": 436467,
      "COLUMN_ROW_SETTING": "SKIP_NOTEXIST",
      "COMMENTINFO": null,
      "IS_RUNNABLE": null,
      "RUN_ORDER": 25,
      "VALUE_SETTING": null
    },
    {
      "dataForDataSets": [
        {
          "Data_Setting_Id": 291901,
          "DATASETVALUE": null,
          "DATA_SUMMARY_ID": 436377,
          "SKIP": 0,
          "STEPS_ID": 436467
        },
        {
          "Data_Setting_Id": 291903,
          "DATASETVALUE": null,
          "DATA_SUMMARY_ID": 436382,
          "SKIP": 0,
          "STEPS_ID": 436467
        },
        {
          "Data_Setting_Id": 291902,
          "DATASETVALUE": null,
          "DATA_SUMMARY_ID": 436378,
          "SKIP": 0,
          "STEPS_ID": 436467
        }
      ],
      "recordStatus": 0,
      "TEST_CASE_ID": 3086,
      "TEST_CASE_NAME": "Futures Trd Action Util",
      "KEY_WORD_ID": 4,
      "KEY_WORD_NAME": "ClickButton",
      "OBJECT_HAPPY_NAME": "CLOSE_BUTTON",
      "OBJECT_ID": 40727,
      "OBJECT_TYPE": "Summit Start",
      "QUICK_ACCESS": "swfname:=_closeButton\nswftypename:=Summit.Framework.DesktopContent.ImageButton\nindex:=0",
      "ENUM_TYPE": null,
      "APPLICATION_ID": 194,
      "OBJECT_NAME_ID": 30430,
      "TYPE_NAME": "SwfButton",
      "STEPS_ID": 436467,
      "COLUMN_ROW_SETTING": "SKIP_NOTEXIST",
      "COMMENTINFO": null,
      "IS_RUNNABLE": null,
      "RUN_ORDER": 25,
      "VALUE_SETTING": null
    },
    {
      "dataForDataSets": [
        {
          "Data_Setting_Id": 291904,
          "DATASETVALUE": null,
          "DATA_SUMMARY_ID": 436377,
          "SKIP": 0,
          "STEPS_ID": 436468
        },
        {
          "Data_Setting_Id": 291906,
          "DATASETVALUE": null,
          "DATA_SUMMARY_ID": 436382,
          "SKIP": 0,
          "STEPS_ID": 436468
        },
        {
          "Data_Setting_Id": 291905,
          "DATASETVALUE": null,
          "DATA_SUMMARY_ID": 436378,
          "SKIP": 0,
          "STEPS_ID": 436468
        }
      ],
      "recordStatus": 0,
      "TEST_CASE_ID": 3086,
      "TEST_CASE_NAME": "Futures Trd Action Util",
      "KEY_WORD_ID": 38,
      "KEY_WORD_NAME": "Dismiss",
      "OBJECT_HAPPY_NAME": null,
      "OBJECT_ID": -1,
      "OBJECT_TYPE": null,
      "QUICK_ACCESS": null,
      "ENUM_TYPE": null,
      "APPLICATION_ID": -1,
      "OBJECT_NAME_ID": -1,
      "TYPE_NAME": " ",
      "STEPS_ID": 436468,
      "COLUMN_ROW_SETTING": null,
      "COMMENTINFO": null,
      "IS_RUNNABLE": null,
      "RUN_ORDER": 26,
      "VALUE_SETTING": null
    },
    {
      "dataForDataSets": [
        {
          "Data_Setting_Id": 291907,
          "DATASETVALUE": null,
          "DATA_SUMMARY_ID": 436377,
          "SKIP": 0,
          "STEPS_ID": 436469
        },
        {
          "Data_Setting_Id": 291909,
          "DATASETVALUE": null,
          "DATA_SUMMARY_ID": 436382,
          "SKIP": 0,
          "STEPS_ID": 436469
        },
        {
          "Data_Setting_Id": 291908,
          "DATASETVALUE": null,
          "DATA_SUMMARY_ID": 436378,
          "SKIP": 0,
          "STEPS_ID": 436469
        }
      ],
      "recordStatus": 0,
      "TEST_CASE_ID": 3086,
      "TEST_CASE_NAME": "Futures Trd Action Util",
      "KEY_WORD_ID": 4,
      "KEY_WORD_NAME": "ClickButton",
      "OBJECT_HAPPY_NAME": "CLOSE_BUTTON",
      "OBJECT_ID": 32409,
      "OBJECT_TYPE": "Summit Start",
      "QUICK_ACCESS": "swfname:=_closeButton\nswftypename:=Summit.Framework.DesktopContent.ImageButton\nindex:=0",
      "ENUM_TYPE": null,
      "APPLICATION_ID": 193,
      "OBJECT_NAME_ID": 30430,
      "TYPE_NAME": "SwfButton",
      "STEPS_ID": 436469,
      "COLUMN_ROW_SETTING": "SKIP_NOTEXIST",
      "COMMENTINFO": null,
      "IS_RUNNABLE": null,
      "RUN_ORDER": 27,
      "VALUE_SETTING": null
    },
    {
      "dataForDataSets": [
        {
          "Data_Setting_Id": 291907,
          "DATASETVALUE": null,
          "DATA_SUMMARY_ID": 436377,
          "SKIP": 0,
          "STEPS_ID": 436469
        },
        {
          "Data_Setting_Id": 291909,
          "DATASETVALUE": null,
          "DATA_SUMMARY_ID": 436382,
          "SKIP": 0,
          "STEPS_ID": 436469
        },
        {
          "Data_Setting_Id": 291908,
          "DATASETVALUE": null,
          "DATA_SUMMARY_ID": 436378,
          "SKIP": 0,
          "STEPS_ID": 436469
        }
      ],
      "recordStatus": 0,
      "TEST_CASE_ID": 3086,
      "TEST_CASE_NAME": "Futures Trd Action Util",
      "KEY_WORD_ID": 4,
      "KEY_WORD_NAME": "ClickButton",
      "OBJECT_HAPPY_NAME": "CLOSE_BUTTON",
      "OBJECT_ID": 40727,
      "OBJECT_TYPE": "Summit Start",
      "QUICK_ACCESS": "swfname:=_closeButton\nswftypename:=Summit.Framework.DesktopContent.ImageButton\nindex:=0",
      "ENUM_TYPE": null,
      "APPLICATION_ID": 194,
      "OBJECT_NAME_ID": 30430,
      "TYPE_NAME": "SwfButton",
      "STEPS_ID": 436469,
      "COLUMN_ROW_SETTING": "SKIP_NOTEXIST",
      "COMMENTINFO": null,
      "IS_RUNNABLE": null,
      "RUN_ORDER": 27,
      "VALUE_SETTING": null
    },
    {
      "dataForDataSets": [
        {
          "Data_Setting_Id": 291910,
          "DATASETVALUE": null,
          "DATA_SUMMARY_ID": 436377,
          "SKIP": 0,
          "STEPS_ID": 436470
        },
        {
          "Data_Setting_Id": 291912,
          "DATASETVALUE": null,
          "DATA_SUMMARY_ID": 436382,
          "SKIP": 0,
          "STEPS_ID": 436470
        },
        {
          "Data_Setting_Id": 291911,
          "DATASETVALUE": null,
          "DATA_SUMMARY_ID": 436378,
          "SKIP": 0,
          "STEPS_ID": 436470
        }
      ],
      "recordStatus": 0,
      "TEST_CASE_ID": 3086,
      "TEST_CASE_NAME": "Futures Trd Action Util",
      "KEY_WORD_ID": 38,
      "KEY_WORD_NAME": "Dismiss",
      "OBJECT_HAPPY_NAME": null,
      "OBJECT_ID": -1,
      "OBJECT_TYPE": null,
      "QUICK_ACCESS": null,
      "ENUM_TYPE": null,
      "APPLICATION_ID": -1,
      "OBJECT_NAME_ID": -1,
      "TYPE_NAME": " ",
      "STEPS_ID": 436470,
      "COLUMN_ROW_SETTING": null,
      "COMMENTINFO": null,
      "IS_RUNNABLE": null,
      "RUN_ORDER": 28,
      "VALUE_SETTING": null
    }
  ]
}